{"all_time":{"channel":{"device":{"100":11,"101":12701,"102":1762,"103":751,"104":13511,"105":1377},"os":{"1":429,"2":11678,"4":8908,"5":6403,"9":638,"10":358,"12":225,"13":6,"17":378,"19":432,"21":36,"22":2,"26":254,"27":15,"28":61,"29":175,"30":86,"31":29}},"videos":{"-3EjJEa_9FY":{"device":{"101":1,"104":2},"os":{"2":1,"4":2}},"-9wEv6t9EUM":{"device":{"101":5,"104":3},"os":{"2":5,"4":1,"5":2}},"-dJ8qzKSMEI":{"device":{"101":12,"102":2,"104":4},"os":{"2":12,"4":3,"5":1,"26":1,"29":1}},"-nfSZAxrKeE":{"device":{"101":1,"102":3,"104":3,"105":2},"os":{"2":1,"4":2,"5":3,"19":2,"29":1}},"-wi95pfC39s":{"device":{"101":6,"104":5},"os":{"2":6,"4":2,"5":3}},"00LZPcwzJVU":{"device":{"101":1,"104":7},"os":{"2":1,"4":6,"5":1}},"0CwqSvbb_gg":{"device":{"100":1,"101":36,"102":1,"103":2,"104":45},"os":{"1":2,"2":35,"4":21,"5":24,"9":1,"10":2}},"0HefYbtHZvU":{"device":{"101":3},"os":{"2":3}},"0L7OJ2Y44WE":{"device":{"101":2,"102":4,"103":5,"104":4,"105":4},"os":{"2":2,"4":6,"5":2,"10":5,"12":1,"19":1,"26":2}},"115HiW_eJJs":{"device":{"105":2},"os":{"4":2}},"1HO0aEv_Tzc":{"device":{"101":35,"102":3,"104":22,"105":3},"os":{"1":1,"2":35,"4":17,"5":8,"19":1,"29":1}},"1J6rolJBREU":{"device":{"101":1,"102":1,"104":1},"os":{"5":1,"9":1,"12":1}},"1LfsXaLm_P0":{"device":{"104":2},"os":{"4":2}},"1k2xQeGTTHs":{"device":{"104":2},"os":{"4":2}},"1vXOHKdcX7o":{"device":{"101":1,"103":1,"104":3,"105":1},"os":{"2":1,"4":2,"5":2,"10":1}},"23hyqJp9-lE":{"device":{"101":16,"104":10},"os":{"2":12,"4":8,"5":2,"9":4}},"26f_oIZH6ug":{"device":{"104":1},"os":{"4":1}},"26ftkHABnVg":{"device":{"101":12,"104":36,"105":2},"os":{"1":1,"2":8,"4":13,"5":25,"9":2,"30":1}},"2Cve8HMD3r4":{"device":{"101":6,"103":1,"104":5,"105":1},"os":{"2":6,"4":2,"5":4,"17":1}},"2XkcnarPcfs":{"device":{"104":10,"105":5},"os":{"4":15}},"2gZvSk6btFc":{"device":{"101":168,"102":16,"103":1,"104":63,"105":12},"os":{"1":5,"2":155,"4":56,"5":25,"9":7,"12":2,"17":1,"19":3,"26":2,"29":3,"30":1}},"2nsgqcGrp6s":{"device":{"101":1,"103":1,"104":10,"105":1},"os":{"2":1,"4":6,"5":5,"10":1}},"3-S2Whrzitw":{"device":{"101":3,"103":3,"104":6,"105":1},"os":{"2":1,"4":2,"5":5,"9":2,"10":3}},"38PxRLbK55U":{"device":{"101":9,"102":1,"103":1,"104":6},"os":{"1":1,"2":8,"4":5,"5":1,"17":1,"19":1}},"3ByYahv-7BA":{"device":{"101":138,"102":1,"104":52},"os":{"1":2,"2":134,"4":26,"5":26,"9":2,"29":1}},"3CZZ47LWegk":{"device":{"101":1},"os":{"2":1}},"3DVZS29lVv0":{"device":{"102":1,"103":1,"104":9},"os":{"1":1,"4":5,"5":4,"17":1}},"3GYBR2-GuzU":{"device":{"104":1},"os":{"4":1}},"3PHRIerzzIw":{"device":{"101":1,"104":10},"os":{"2":1,"4":6,"5":4}},"3Qoxr0RZPbA":{"device":{"101":1,"104":1},"os":{"4":1,"9":1}},"3YjbU1TjcPQ":{"device":{"101":2,"104":5},"os":{"2":2,"4":5}},"3lEBobiGGiw":{"device":{"101":44,"104":2,"105":1},"os":{"2":40,"4":1,"5":2,"9":4}},"4-X8kYgDNII":{"device":{"101":2,"104":2},"os":{"2":2,"5":2}},"47dWPH0gK8Q":{"device":{"101":11,"104":22},"os":{"1":1,"2":10,"4":11,"5":11}},"4AWSe96znVs":{"device":{"101":3,"102":1,"103":1,"104":3,"105":1},"os":{"2":3,"4":2,"5":2,"17":1,"19":1}},"4Bly1zF66L8":{"device":{"101":1,"103":3,"104":9,"105":3},"os":{"2":1,"4":5,"5":7,"10":1,"17":2}},"4MFGQA5mNoQ":{"device":{"101":19,"102":4,"104":16,"105":1},"os":{"2":18,"4":9,"5":8,"9":1,"26":4}},"4RBo2WhsWGY":{"device":{"101":2,"102":1,"103":3,"104":7,"105":2},"os":{"2":1,"4":5,"5":4,"9":1,"10":3,"26":1}},"4RYKHoKMjC4":{"device":{"101":5,"104":23},"os":{"2":5,"4":14,"5":9}},"4VHQaw2nRSk":{"device":{"101":4},"os":{"2":4}},"4owwPSS1SdM":{"device":{"101":3,"104":1},"os":{"2":2,"5":1,"9":1}},"4qYYWH2Km4g":{"device":{"104":3},"os":{"5":3}},"4uzwSeHNyFk":{"device":{"101":7,"102":2,"104":8},"os":{"2":7,"4":2,"5":6,"19":2}},"50_H0j9eEto":{"device":{"101":1,"104":3},"os":{"2":1,"4":1,"5":2}},"561WFdai_mI":{"device":{"104":1},"os":{"4":1}},"5Bu7AhTvSfU":{"device":{"101":1,"102":1,"104":4},"os":{"2":1,"4":4,"19":1}},"5Ntxn2faXt8":{"device":{"101":3033,"102":31,"103":8,"104":1323,"105":67},"os":{"1":41,"2":2966,"4":636,"5":761,"9":27,"10":4,"13":2,"17":4,"19":9,"26":4,"28":1,"29":2,"30":4,"31":1}},"5Q_rZzh8NrE":{"device":{"101":2},"os":{"2":2}},"5Qc0KQiy_9Q":{"device":{"104":3},"os":{"4":2,"5":1}},"5RGZweasTWs":{"device":{"102":1,"104":3},"os":{"4":3,"26":1}},"5Y3EsWmOPZM":{"device":{"101":101,"102":30,"103":10,"104":110,"105":22},"os":{"1":6,"2":88,"4":90,"5":50,"9":6,"10":8,"12":4,"13":1,"17":2,"19":6,"21":1,"26":2,"28":4,"30":4,"31":1}},"5ahyyMboTbE":{"device":{"101":145,"102":67,"103":49,"104":199,"105":41},"os":{"1":11,"2":124,"4":176,"5":78,"9":15,"10":23,"12":7,"17":26,"19":17,"21":4,"26":9,"28":1,"29":8,"30":1,"31":1}},"5dDwVcJT7tA":{"device":{"104":1},"os":{"5":1}},"5jcApdKyZ-I":{"device":{"101":2},"os":{"2":2}},"5nGSY6YxMBE":{"device":{"101":2,"102":1,"103":1,"104":11},"os":{"2":2,"4":7,"5":4,"17":1,"19":1}},"5w4RjcxqV-o":{"device":{"101":195,"102":47,"103":23,"104":159,"105":23},"os":{"1":14,"2":165,"4":124,"5":67,"9":18,"10":1,"12":7,"13":1,"17":22,"19":4,"26":10,"28":4,"29":4,"30":2,"31":4}},"5wnZYrZ2ZvI":{"device":{"101":28,"102":4,"103":33,"104":71,"105":4},"os":{"2":26,"4":50,"5":26,"9":2,"10":32,"12":1,"17":1,"26":1,"28":1}},"67ifyj_oxYQ":{"device":{"101":2,"102":1},"os":{"2":2,"19":1}},"6Ch39rrY2PY":{"device":{"101":40,"104":15},"os":{"2":39,"4":5,"5":10,"9":1}},"6Nj6vwLk3rM":{"device":{"104":3},"os":{"4":3}},"6ShaabGAA1I":{"device":{"101":164,"102":27,"103":14,"104":187,"105":9},"os":{"1":5,"2":147,"4":139,"5":64,"9":13,"10":3,"12":4,"17":11,"19":5,"22":1,"26":3,"28":2,"29":1,"31":3}},"6b4QUPNjG00":{"device":{"101":1},"os":{"2":1}},"7-Rftp6KFn8":{"device":{"101":5,"104":1},"os":{"2":5,"5":1}},"756xyJRy2T4":{"device":{"101":9,"104":2},"os":{"2":7,"4":1,"5":1,"9":2}},"7Ez-74SuHZ8":{"device":{"101":59,"102":1,"104":7},"os":{"1":2,"2":55,"4":5,"5":2,"9":2,"12":1}},"7f9k1ruyX54":{"device":{"101":2,"104":4},"os":{"2":2,"4":2,"5":2}},"7lHQ-KfpY2o":{"device":{"101":118,"102":77,"103":32,"104":376,"105":43},"os":{"1":8,"2":99,"4":356,"5":83,"9":12,"10":13,"12":8,"13":1,"17":18,"19":16,"26":15,"27":1,"28":3,"29":12,"30":1}},"7mXcpZKG_18":{"device":{"104":1},"os":{"4":1}},"7sYn3ZCAhKg":{"device":{"101":1},"os":{"2":1}},"7u5OzzRKiA4":{"device":{"105":1},"os":{"4":1}},"7yIZo3YBxYo":{"device":{"101":12,"102":2,"103":1,"104":11,"105":4},"os":{"2":6,"4":9,"5":6,"9":6,"10":1,"19":1,"26":1}},"82A8enPYdZE":{"device":{"101":1},"os":{"2":1}},"8GdD4czvJro":{"device":{"101":34,"102":13,"103":1,"104":64,"105":5},"os":{"1":14,"2":19,"4":63,"5":14,"9":1,"12":1,"17":1,"26":2,"28":2}},"8WX54HD_LOs":{"device":{"101":1,"103":1,"104":3,"105":1},"os":{"2":1,"4":2,"5":2,"17":1}},"8w-FuJNlm-o":{"device":{"101":189,"102":13,"103":1,"104":523,"105":47},"os":{"1":1,"2":171,"4":358,"5":217,"9":13,"10":1,"12":2,"19":3,"26":2,"30":4,"31":1}},"9Dcery3yjBo":{"device":{"101":7,"102":1,"104":56,"105":2},"os":{"2":6,"4":31,"5":27,"9":1,"29":1}},"9JxwIbZ412g":{"device":{"101":2},"os":{"2":2}},"9ODh2yjrCPA":{"device":{"101":6,"102":7,"103":2,"104":15,"105":7},"os":{"2":4,"4":14,"5":10,"10":1,"12":1,"17":1,"19":2,"26":1,"29":1,"30":2}},"9Yam9_xQJI8":{"device":{"101":149,"102":20,"103":11,"104":178,"105":22},"os":{"1":7,"2":129,"4":109,"5":96,"9":11,"10":6,"12":6,"17":5,"19":4,"26":1,"29":2,"30":3,"31":1}},"A-ab2t50WUY":{"device":{"101":13,"102":6,"103":3,"104":13,"105":4},"os":{"2":13,"4":10,"5":9,"10":2,"17":1,"19":1,"26":2,"29":1}},"A9hK0en2Uqg":{"device":{"101":3,"104":4},"os":{"2":3,"4":2,"5":2}},"AAX9HV6mOCg":{"device":{"101":2,"104":1},"os":{"2":2,"4":1}},"ABBnd9c6ImI":{"device":{"104":1},"os":{"5":1}},"AJ_fphmB848":{"device":{"101":1},"os":{"2":1}},"AQdnbOgM71k":{"device":{"101":483,"102":32,"103":6,"104":416,"105":57},"os":{"1":6,"2":462,"4":264,"5":212,"9":13,"10":2,"12":4,"17":3,"19":13,"26":8,"27":1,"29":2,"30":4}},"AaejCpNADp8":{"device":{"101":1,"103":3,"104":3,"105":2},"os":{"2":1,"4":3,"5":2,"10":3}},"AvcVvsrk8dE":{"device":{"101":14,"104":7},"os":{"2":13,"4":6,"5":1,"9":1}},"B5--JAJjyw8":{"device":{"101":5},"os":{"2":5}},"BHHckNXaeRI":{"device":{"104":3},"os":{"4":1,"5":2}},"BI2u1YDcrdM":{"device":{"101":1,"104":2,"105":1},"os":{"4":1,"5":2,"30":1}},"BKMv6AxH5CI":{"device":{"101":1},"os":{"30":1}},"BMIcOvi0w20":{"device":{"104":1},"os":{"4":1}},"BRUSFtx-H3U":{"device":{"101":3,"102":3,"103":1,"104":4,"105":2},"os":{"1":1,"2":3,"4":3,"5":3,"10":1,"12":2}},"BcOZT21IDGI":{"device":{"101":1,"104":2},"os":{"2":1,"4":2}},"Be_-4zjAbc0":{"device":{"101":24,"102":8,"103":14,"104":49,"105":6},"os":{"1":1,"2":23,"4":28,"5":28,"9":1,"10":4,"17":10,"19":4,"26":1,"29":1}},"BvFP14yAD8I":{"device":{"101":1},"os":{"2":1}},"ByYu9JrTDrQ":{"device":{"101":5,"102":1,"103":1,"104":1},"os":{"2":5,"5":1,"12":1,"17":1}},"C91-OR-s-UY":{"device":{"101":1,"104":2},"os":{"2":1,"4":2}},"CCjPVVUO0MY":{"device":{"101":5,"102":1,"104":3},"os":{"2":4,"4":1,"5":2,"9":1,"19":1}},"CD_z7fOmZYE":{"device":{"101":4,"104":3},"os":{"1":1,"2":2,"4":2,"5":1,"9":1}},"CajKQ01dCP0":{"device":{"104":1},"os":{"4":1}},"CdlWvITC8qw":{"device":{"100":2,"101":84,"102":15,"103":4,"104":73,"105":8},"os":{"1":3,"2":83,"4":55,"5":26,"9":1,"10":1,"12":3,"17":3,"19":8,"21":1,"29":2}},"Cq-Ajxe2Jo8":{"device":{"101":4,"104":2},"os":{"2":4,"4":1,"5":1}},"Crkib9LfwEM":{"device":{"101":1,"103":1,"104":3},"os":{"2":1,"4":3,"17":1}},"D42bM3u0InI":{"device":{"101":18,"102":7,"104":18,"105":1},"os":{"1":3,"2":13,"4":14,"5":6,"9":5,"12":1,"19":1,"26":1}},"DYg4XrwkM9Q":{"device":{"101":4,"103":1,"104":7,"105":1},"os":{"2":4,"4":4,"5":4,"17":1}},"Df-Sfz_vLJ4":{"device":{"101":1,"104":2},"os":{"2":1,"4":1,"5":1}},"DobDHytF5OY":{"device":{"101":1},"os":{"2":1}},"DvA1ZefR7wQ":{"device":{"101":1},"os":{"9":1}},"E3zJyj3RYR4":{"device":{"101":2,"102":1,"104":3},"os":{"2":2,"4":1,"5":2,"19":1}},"E61VDhCxwWI":{"device":{"101":39,"102":11,"103":22,"104":314,"105":30},"os":{"1":2,"2":33,"4":131,"5":217,"9":2,"10":17,"17":5,"19":5,"29":2,"30":2}},"EEjJhrqkrvo":{"device":{"101":1,"102":1,"104":5},"os":{"4":5,"9":1,"12":1}},"EVSDFA42HPE":{"device":{"102":1},"os":{"19":1}},"EePeG9dDG8c":{"device":{"101":5,"102":1,"103":1,"104":17,"105":1},"os":{"2":5,"4":17,"5":2,"27":1}},"EkAM7FFAIZs":{"device":{"101":4},"os":{"2":4}},"EmKTi4GAj1s":{"device":{"102":1,"104":9},"os":{"4":5,"5":4,"19":1}},"F3l2CZE3-_0":{"device":{"104":1},"os":{"5":1}},"F7KGvcgEMj8":{"device":{"101":5,"104":14,"105":1},"os":{"2":4,"4":7,"5":8,"9":1}},"FAu1ag2mC_4":{"device":{"104":2},"os":{"4":2}},"FKDVSeBD_IQ":{"device":{"101":1},"os":{"2":1}},"FPYjEhH5Viw":{"device":{"104":6,"105":2},"os":{"4":8}},"FQhNwkGPrtU":{"device":{"101":2},"os":{"2":2}},"FiUedyH1fVk":{"device":{"102":1},"os":{"4":1}},"FxxONV7QhiA":{"device":{"104":3},"os":{"4":3}},"FzOTKEQZ-hY":{"device":{"101":1,"104":1},"os":{"2":1,"4":1}},"GMFAiPaUbLA":{"device":{"101":35,"104":19},"os":{"1":1,"2":34,"4":10,"5":9}},"GPENFuAFawI":{"device":{"102":1,"103":1,"104":4},"os":{"4":3,"5":1,"10":1,"31":1}},"GTVYSV1oE2E":{"device":{"101":3,"104":3},"os":{"2":3,"4":1,"5":2}},"GbXE9PAzXRI":{"device":{"101":4,"104":4},"os":{"2":2,"4":2,"5":2,"9":2}},"Gca1yHItwd0":{"device":{"101":7,"104":3},"os":{"2":7,"4":3}},"GsjT4T6B_S8":{"device":{"104":4},"os":{"4":4}},"GvmXD9ia4I8":{"device":{"101":89,"102":14,"104":36,"105":4},"os":{"2":81,"4":25,"5":18,"9":8,"12":2,"19":4,"26":2,"28":1,"29":1,"31":1}},"GxMsyWHTR1c":{"device":{"101":1,"104":1,"105":2},"os":{"2":1,"4":2,"5":1}},"HAy1IwAn1O0":{"device":{"101":126,"102":16,"103":8,"104":65,"105":8},"os":{"1":8,"2":114,"4":46,"5":33,"9":6,"10":5,"12":2,"17":3,"19":3,"28":1,"29":2}},"HGZCTzDL01w":{"device":{"103":1},"os":{"10":1}},"Hdy822qo8lA":{"device":{"104":2},"os":{"4":1,"5":1}},"I0WsADNO_mc":{"device":{"101":188,"102":3,"104":108,"105":5},"os":{"1":1,"2":185,"4":59,"5":55,"9":2,"12":1,"26":1}},"I28qtymZsGQ":{"device":{"102":1},"os":{"1":1}},"I4GB0wucViM":{"device":{"101":4,"105":1},"os":{"2":2,"5":1,"9":2}},"ICTJOHPa1Ag":{"device":{"101":35,"102":1,"104":44,"105":5},"os":{"1":1,"2":29,"4":29,"5":21,"9":5}},"IJiDnjh5k28":{"device":{"101":4,"104":1},"os":{"2":4,"4":1}},"IOwa_0n1dHE":{"device":{"101":12,"102":2,"104":14,"105":3},"os":{"2":10,"4":10,"5":7,"9":1,"12":1,"19":1,"30":1}},"Ictg8L25QM8":{"device":{"102":1,"104":5},"os":{"4":3,"5":3}},"Iui1Q86fRDo":{"device":{"101":5,"104":3},"os":{"2":5,"4":2,"5":1}},"J4hpbb9rRCg":{"device":{"101":4,"104":2},"os":{"2":4,"4":2}},"JP11PpfEHAk":{"device":{"101":1,"105":1},"os":{"2":1,"4":1}},"JUNpp3T0T2Q":{"device":{"101":29,"102":2,"103":2,"104":75,"105":2},"os":{"1":5,"2":25,"4":49,"5":28,"10":2,"19":1}},"J_vdKLo9aYE":{"device":{"101":1},"os":{"2":1}},"JgXeYJrYP3Y":{"device":{"101":1},"os":{"2":1}},"JhIFjQPsEGo":{"device":{"104":3},"os":{"4":2,"5":1}},"JjTSfJy26oI":{"device":{"101":34,"104":6},"os":{"1":2,"2":32,"4":5,"5":1}},"JkKpxFUiOPQ":{"device":{"101":25,"104":5},"os":{"2":25,"4":4,"5":1}},"Jwjfz6CAF1U":{"device":{"101":3,"104":1},"os":{"2":3,"4":1}},"K1-1W4cDC8w":{"device":{"101":1,"104":1},"os":{"2":1,"4":1}},"K21tmxGSg1c":{"device":{"101":15,"102":1,"103":3,"104":17,"105":2},"os":{"2":15,"4":8,"5":11,"10":2,"17":1,"26":1}},"KBhT3_S-Wyc":{"device":{"101":7,"102":1,"103":1,"104":12},"os":{"2":7,"4":8,"5":4,"17":1,"26":1}},"KXx7-M3EAIY":{"device":{"101":5,"104":2},"os":{"2":5,"4":2}},"Kb1o7hXJvv4":{"device":{"101":44,"102":13,"103":5,"104":52,"105":13},"os":{"1":2,"2":42,"4":45,"5":24,"10":4,"17":1,"19":2,"26":3,"29":3,"30":1}},"Kc5LB_Kf5iQ":{"device":{"104":4},"os":{"4":3,"5":1}},"KlAgm3lGFFQ":{"device":{"101":5,"102":3,"104":5,"105":1},"os":{"2":5,"4":5,"5":2,"26":2}},"Kxt1oWOgvoI":{"device":{"101":110,"102":15,"104":52,"105":12},"os":{"1":8,"2":95,"4":43,"5":24,"9":8,"12":1,"19":6,"26":2,"31":2}},"L8W_tyWswvQ":{"device":{"101":5,"102":4,"103":1,"104":11,"105":1},"os":{"1":1,"2":4,"4":6,"5":6,"9":1,"17":1,"26":3}},"LANgtT8CJHU":{"device":{"101":11,"103":2,"104":13},"os":{"2":8,"4":11,"5":2,"9":3,"10":2}},"LPsOL4MCO5A":{"device":{"101":3,"102":2,"104":3},"os":{"2":3,"4":3,"12":1,"26":1}},"LRnNHhWu2eA":{"device":{"101":1},"os":{"2":1}},"LherFWJgr9M":{"device":{"101":4,"102":4,"103":1,"104":6,"105":2},"os":{"2":4,"4":3,"5":5,"10":1,"21":1,"26":1,"29":2}},"LzkQPjzP--E":{"device":{"104":2},"os":{"4":2}},"MLxe1ridlRY":{"device":{"101":4,"104":1},"os":{"2":4,"4":1}},"MMunBaTQL64":{"device":{"101":13,"102":1,"103":2,"104":88,"105":4},"os":{"1":1,"2":9,"4":46,"5":46,"9":3,"10":1,"17":1,"28":1}},"MOrj_qRc3zQ":{"device":{"101":1},"os":{"2":1}},"MXrhaajx594":{"device":{"101":11,"102":21,"103":4,"104":31,"105":7},"os":{"2":11,"4":32,"5":13,"10":3,"17":1,"19":3,"21":11}},"MlzPM8jR0Gk":{"device":{"100":1,"101":11},"os":{"1":1,"2":11}},"NYgA50vM9-Y":{"device":{"101":7,"104":6},"os":{"2":7,"4":4,"5":2}},"Nq3FE46itYg":{"device":{"101":40,"104":6,"105":1},"os":{"1":1,"2":38,"4":5,"5":2,"9":1}},"Nr_298OOamA":{"device":{"102":3,"104":1},"os":{"4":1,"19":3}},"NzdorOVDlw0":{"device":{"101":13,"102":1,"104":13},"os":{"1":1,"2":11,"4":5,"5":9,"9":1}},"O668BaDTXIo":{"device":{"101":1},"os":{"2":1}},"OCenVqWNt7g":{"device":{"104":3},"os":{"4":1,"5":2}},"OHT33Pv7Du0":{"device":{"101":1},"os":{"2":1}},"OJnD6iCI1yM":{"device":{"100":1,"101":32,"104":23,"105":2},"os":{"1":2,"2":30,"4":21,"5":4,"9":1}},"OOoyvAq-s2Y":{"device":{"101":1,"104":1},"os":{"2":1,"4":1}},"Ob8GV-84B8o":{"device":{"104":1},"os":{"5":1}},"OopDjsg19UQ":{"device":{"101":21,"102":7,"103":12,"104":36,"105":7},"os":{"1":1,"2":19,"4":24,"5":19,"9":2,"10":6,"17":6,"19":2,"26":1,"28":1,"29":2}},"P2iT1TUoklM":{"device":{"101":1},"os":{"2":1}},"P6yTTTqGmT0":{"device":{"101":18,"102":4,"103":1,"104":65,"105":4},"os":{"2":16,"4":54,"5":18,"9":2,"10":1,"19":1}},"P7g39CZtRRg":{"device":{"104":1},"os":{"4":1}},"PNjiwlnZ3Lc":{"device":{"104":4},"os":{"4":1,"5":3}},"Pb-4FMXIz40":{"device":{"101":9,"102":9,"103":3,"104":51,"105":2},"os":{"1":1,"2":8,"4":35,"5":22,"9":1,"10":1,"17":2,"26":4}},"PbbfmaZ4JxY":{"device":{"101":5,"104":2},"os":{"2":4,"5":2,"9":1}},"PhsQA0sYjsc":{"device":{"101":20,"104":3},"os":{"2":20,"4":3}},"PtZsi7HFsKk":{"device":{"101":4,"102":1,"104":4},"os":{"2":4,"4":4,"28":1}},"Q0BZe9WN1y8":{"device":{"101":34,"102":8,"103":4,"104":82,"105":8},"os":{"1":4,"2":29,"4":54,"5":40,"9":1,"10":1,"12":2,"17":3,"26":1,"29":1}},"Q77jfi8FAC0":{"device":{"101":20,"102":3,"104":8},"os":{"2":16,"4":8,"5":1,"9":4,"19":2}},"Q9M_HL1L9fs":{"device":{"101":2,"104":1},"os":{"2":2,"5":1}},"QNiLsEGVV0k":{"device":{"101":10,"104":5},"os":{"2":10,"5":5}},"Q_WB-lnyyIo":{"device":{"101":29,"102":2,"103":1,"104":17,"105":4},"os":{"1":1,"2":27,"4":15,"5":7,"9":1,"17":1,"26":1}},"QbZ1hsNMdkU":{"device":{"101":1},"os":{"2":1}},"QeOeqfvlbbg":{"device":{"101":4,"102":2,"104":5},"os":{"2":1,"4":4,"5":1,"9":3,"19":1,"29":1}},"QuPSPzhEJJU":{"device":{"101":21,"102":3,"103":5,"104":16},"os":{"1":2,"2":18,"4":11,"5":5,"9":1,"10":2,"17":3,"19":1,"26":1,"29":1}},"R-64MF2ooWw":{"device":{"104":4},"os":{"4":2,"5":2}},"RBLcszExDvQ":{"device":{"104":1},"os":{"4":1}},"RCUWuigh49Q":{"device":{"101":21,"102":3,"103":5,"104":28,"105":6},"os":{"1":1,"2":20,"4":21,"5":15,"10":1,"17":4,"19":1}},"RRh-oOwZ_s0":{"device":{"101":1},"os":{"2":1}},"RV4K2ErGgA0":{"device":{"101":3,"104":2,"105":1},"os":{"1":1,"2":1,"4":1,"5":2,"9":1}},"RZEvZAC-ybA":{"device":{"101":1,"102":1},"os":{"2":1,"19":1}},"RfTqo8_Brbg":{"device":{"101":5,"103":1,"104":4},"os":{"2":5,"4":2,"5":2,"17":1}},"RhcLtnEWDfU":{"device":{"101":11,"104":5,"105":2},"os":{"1":6,"2":5,"4":7}},"RjoE7uPjobs":{"device":{"101":2,"103":2,"104":4,"105":1},"os":{"2":2,"4":3,"5":2,"10":2}},"RufIydXWWmo":{"device":{"101":69,"102":1,"103":5,"104":131,"105":5},"os":{"1":1,"2":67,"4":60,"5":76,"9":1,"17":5,"19":1}},"SBJV7VwLnbM":{"device":{"101":9,"104":2},"os":{"2":9,"4":1,"5":1}},"SE667oAdPGI":{"device":{"101":7,"102":4,"104":2,"105":4},"os":{"2":7,"4":5,"5":1,"19":1,"26":3}},"SFj5gcK_R1g":{"device":{"103":1,"104":1},"os":{"5":1,"10":1}},"SPXWj18a4TM":{"device":{"104":8},"os":{"4":1,"5":7}},"SR7dLH10Eh4":{"device":{"101":1,"104":3},"os":{"2":1,"5":3}},"SY7dJkwvZ8Q":{"device":{"101":5,"104":3},"os":{"2":4,"4":1,"5":2,"9":1}},"SgKD1JbYsgg":{"device":{"105":1},"os":{"4":1}},"SiGTsE2CctY":{"device":{"101":39,"102":13,"104":19,"105":2},"os":{"1":3,"2":31,"4":19,"5":6,"9":5,"12":1,"19":1,"26":3,"28":2,"29":2}},"SpP32-oVgsE":{"device":{"102":1,"104":2},"os":{"1":1,"4":2}},"Sy_vDZ7kTdA":{"device":{"101":3,"102":1,"103":1,"104":3,"105":1},"os":{"2":3,"4":2,"5":2,"17":1,"28":1}},"TMZRIf5agWM":{"device":{"101":2,"102":1,"104":2},"os":{"2":1,"4":2,"5":1,"9":1}},"TNeD_l-uSXM":{"device":{"104":2},"os":{"5":2}},"TZI4wV5kezI":{"device":{"104":2},"os":{"4":2}},"TnZ5NEzngcs":{"device":{"101":181,"102":28,"103":7,"104":328,"105":21},"os":{"1":3,"2":136,"4":205,"5":156,"9":42,"10":2,"12":8,"17":4,"19":6,"26":1,"27":1,"29":1}},"UF0tXQMP_xw":{"device":{"101":3},"os":{"2":3}},"UKa4Y-eq1hw":{"device":{"101":3,"104":6},"os":{"2":3,"4":2,"5":4}},"UX7ZDsIETg0":{"device":{"104":1},"os":{"5":1}},"Ubo73CUafQ4":{"device":{"101":1,"104":2,"105":1},"os":{"2":1,"4":2,"5":1}},"UfUEBpO2oCw":{"device":{"101":1,"104":3},"os":{"5":3,"30":1}},"Ul-EO4xFtXs":{"device":{"101":20,"103":1,"104":10,"105":3},"os":{"1":1,"2":14,"4":10,"5":3,"9":4,"17":1,"30":1}},"UrgLSEWPteg":{"device":{"101":1},"os":{"2":1}},"V8THWV7wf3c":{"device":{"101":11,"102":2,"103":3,"104":12,"105":11},"os":{"2":11,"4":16,"5":7,"10":2,"17":1,"26":2}},"VhHG2dLDCEc":{"device":{"103":1,"104":1},"os":{"4":1,"17":1}},"VknTKStx1io":{"device":{"101":9,"104":9,"105":3},"os":{"1":1,"2":8,"4":1,"5":11}},"VnAnNOpRDNc":{"device":{"101":18,"102":2,"103":1,"104":12},"os":{"1":2,"2":16,"4":10,"5":2,"10":1,"12":1,"19":1}},"VrslB00QqRM":{"device":{"102":1},"os":{"22":1}},"W_rKM3cjzhg":{"device":{"101":6,"102":1,"104":3},"os":{"2":6,"4":3,"5":1}},"X1mnFMom5ok":{"device":{"101":6,"102":13,"103":3,"104":28,"105":3},"os":{"2":6,"4":16,"5":16,"10":1,"12":4,"17":2,"19":4,"26":3,"29":1}},"XFuEE08kuYU":{"device":{"101":1,"102":1,"104":2},"os":{"2":1,"4":1,"5":1,"26":1}},"XQLgV99UScU":{"device":{"104":2},"os":{"4":1,"5":1}},"XSgRXpf4tMg":{"device":{"101":1},"os":{"2":1}},"XYCsomcgiK8":{"device":{"101":4,"104":1},"os":{"2":4,"5":1}},"XeV_qdcRyYY":{"device":{"101":1,"102":1,"104":1},"os":{"4":1,"19":1,"30":1}},"XzAx_d7EF6s":{"device":{"101":4,"102":1,"104":3,"105":1},"os":{"2":4,"4":1,"5":3,"19":1}},"YDcuYSupxis":{"device":{"101":4,"104":4,"105":1},"os":{"2":4,"4":4,"5":1}},"YFHijQYh5qI":{"device":{"101":16,"104":5},"os":{"2":14,"4":2,"5":3,"9":2}},"YGS9ysr8KTE":{"device":{"101":2},"os":{"2":2}},"YXM1NEYHgbI":{"device":{"104":1},"os":{"5":1}},"YdVJZJtu6TQ":{"device":{"101":9,"104":12},"os":{"2":8,"4":9,"5":3,"9":1}},"Z4OglYP-gPk":{"device":{"101":1,"105":2},"os":{"2":1,"4":2}},"Z75c4VT1hjI":{"device":{"101":2,"102":1,"104":7},"os":{"2":2,"4":2,"5":5,"19":1}},"ZivaBPZE8fA":{"device":{"101":31,"102":8,"103":4,"104":100,"105":10},"os":{"1":2,"2":26,"4":57,"5":54,"9":5,"10":2,"17":2,"19":3,"29":2}},"Zk4W2GnXK1g":{"device":{"101":5,"102":1,"104":7,"105":3},"os":{"2":5,"4":6,"5":4,"19":1}},"ZluTGysYIw8":{"device":{"101":8,"102":1,"104":39,"105":2},"os":{"1":1,"2":8,"4":23,"5":18}},"_-omWaKuN3c":{"device":{"101":1,"104":1},"os":{"2":1,"4":1}},"_MBZMcoz7so":{"device":{"101":1,"103":1,"104":4,"105":1},"os":{"2":1,"4":3,"5":2,"10":1}},"_PS0dSP8FS0":{"device":{"101":2,"104":6},"os":{"2":2,"4":4,"5":2}},"_V82MwbAduc":{"device":{"104":1},"os":{"4":1}},"_dqUwHra3II":{"device":{"101":1,"104":1},"os":{"1":1,"5":1}},"_pOVXwY6HWo":{"device":{"101":2,"103":1},"os":{"9":2,"10":1}},"aA68xBsGr2s":{"device":{"101":4,"102":3,"103":1,"104":3,"105":1},"os":{"2":4,"4":1,"5":3,"10":1,"12":1,"19":1,"26":1}},"aBeT6XLdtUE":{"device":{"100":1,"101":268,"102":139,"103":56,"104":683,"105":92},"os":{"1":23,"2":240,"4":457,"5":346,"9":16,"10":23,"12":17,"17":31,"19":37,"21":1,"26":26,"27":2,"28":4,"29":9,"30":7}},"agiuuiZRe7A":{"device":{"104":1},"os":{"4":1}},"aiZR53aD8ps":{"device":{"101":1,"104":5},"os":{"4":4,"5":1,"9":1}},"azb8V9exqBg":{"device":{"101":1},"os":{"2":1}},"b20qh3rko6o":{"device":{"101":7,"102":1,"104":3},"os":{"1":3,"2":4,"4":2,"5":1,"19":1}},"b6AeB2YFv2I":{"device":{"104":1},"os":{"4":1}},"bBD9xsUbTsI":{"device":{"101":1},"os":{"2":1}},"bME_-Y4GU0s":{"device":{"101":219,"102":47,"103":2,"104":126,"105":18},"os":{"1":11,"2":192,"4":114,"5":40,"9":11,"10":2,"12":6,"19":18,"26":3,"28":1,"29":5,"30":9}},"bQbmiQrneG0":{"device":{"101":2,"102":1,"104":4},"os":{"2":2,"4":4,"26":1}},"bUbBeTZX_8Q":{"device":{"101":5,"103":2,"104":3,"105":1},"os":{"2":2,"4":3,"5":1,"9":3,"17":2}},"bYy94Hnq9d8":{"device":{"101":1},"os":{"2":1}},"bm_ixy5asSU":{"device":{"102":1,"104":1},"os":{"4":1,"5":1}},"bvAm2rFaB0I":{"device":{"104":7},"os":{"4":4,"5":3}},"bvBVwvtTBhM":{"device":{"101":3,"104":1,"105":1},"os":{"2":3,"4":1,"5":1}},"c0QuKjiPezw":{"device":{"101":1,"102":1,"104":4,"105":1},"os":{"1":1,"4":2,"5":3,"19":1}},"c6lhCOdZlv8":{"device":{"101":5,"102":2,"104":8,"105":2},"os":{"2":5,"4":5,"5":5,"12":1,"19":1}},"c8uwuKfuLyw":{"device":{"104":2},"os":{"4":1,"5":1}},"cOWPIOmhogY":{"device":{"101":1,"104":6},"os":{"2":1,"4":3,"5":3}},"cUNBI3jG6Ps":{"device":{"101":5,"104":1,"105":1},"os":{"2":5,"5":2}},"ccctpVrxqzE":{"device":{"101":2,"104":2},"os":{"2":2,"4":1,"5":1}},"ctP_u1QhWck":{"device":{"101":31,"102":25,"103":15,"104":84,"105":4},"os":{"1":6,"2":25,"4":51,"5":40,"9":1,"10":3,"12":1,"17":12,"19":3,"21":1,"26":9,"28":1,"29":3,"30":1,"31":2}},"cw3dB9y2Sas":{"device":{"101":948,"102":106,"103":68,"104":2024,"105":142},"os":{"1":34,"2":816,"4":1254,"5":944,"9":93,"10":38,"12":14,"17":26,"19":26,"21":3,"26":6,"27":4,"28":3,"29":15,"30":11,"31":1}},"d9HWFXbhcNw":{"device":{"101":1,"104":1,"105":1},"os":{"4":2,"9":1}},"dTIww4RF-CE":{"device":{"104":3},"os":{"4":1,"5":2}},"dYpjpKSzspM":{"device":{"104":2},"os":{"4":2}},"d_D8e_Sxsus":{"device":{"101":20,"102":3,"104":12,"105":4},"os":{"1":1,"2":18,"4":11,"5":6,"9":1,"19":2}},"dcPJP4Acq28":{"device":{"101":7,"102":4,"103":7,"104":12},"os":{"1":1,"2":7,"4":9,"5":3,"17":7,"19":1,"26":2}},"dcwLTJwNsXo":{"device":{"101":8,"103":4,"104":39,"105":2},"os":{"2":8,"4":26,"5":15,"10":4}},"dds-2H1RRNA":{"device":{"102":1,"103":1},"os":{"10":1,"19":1}},"deLBqE8iM3w":{"device":{"101":1,"102":1,"104":6},"os":{"2":1,"4":3,"5":4}},"e4XTAeFJc94":{"device":{"101":2,"104":1},"os":{"2":2,"4":1}},"e5h_fG6sYlU":{"device":{"104":1},"os":{"4":1}},"eDPcV_imXWE":{"device":{"101":39,"102":4,"103":7,"104":50,"105":1},"os":{"2":38,"4":22,"5":29,"9":1,"10":6,"12":2,"17":1,"29":2}},"eT18m4COayU":{"device":{"101":79,"102":3,"103":3,"104":39,"105":2},"os":{"1":3,"2":74,"4":32,"5":9,"9":2,"17":3,"19":3}},"eXOb0ZvpdJ8":{"device":{"101":1,"102":1,"103":1,"104":6},"os":{"2":1,"4":4,"5":2,"12":1,"17":1}},"eYt3XZcfxh4":{"device":{"101":4,"104":2},"os":{"2":4,"4":1,"5":1}},"eeBVFrBCmZs":{"device":{"101":71,"102":10,"103":7,"104":37,"105":8},"os":{"1":2,"2":68,"4":41,"5":7,"9":1,"10":3,"12":1,"17":4,"19":2,"26":1,"28":1,"29":2}},"eeNVDg_guuE":{"device":{"101":19,"102":7,"103":1,"104":30,"105":3},"os":{"1":1,"2":18,"4":24,"5":12,"9":1,"10":1,"19":1,"26":2}},"ejMVm8OFhl8":{"device":{"101":47,"102":3,"104":14,"105":1},"os":{"1":4,"2":38,"4":11,"5":4,"9":5,"29":3}},"et9pKdAzRbs":{"device":{"100":1,"101":138,"102":30,"103":8,"104":391,"105":13},"os":{"1":5,"2":120,"4":241,"5":177,"9":15,"10":2,"12":4,"17":6,"19":4,"26":5,"28":2}},"f9VQ8HQ87dg":{"device":{"101":2},"os":{"2":2}},"fE4JvGH7fU0":{"device":{"102":1,"105":1},"os":{"4":1,"19":1}},"fFnQIu3WSpA":{"device":{"101":3,"104":4,"105":1},"os":{"2":3,"4":3,"5":2}},"fKMrdsDWc6w":{"device":{"101":1,"104":12},"os":{"2":1,"4":8,"5":4}},"fOEn_38g1Hw":{"device":{"101":1,"102":1,"104":2},"os":{"4":2,"5":1,"9":1}},"fOV0uB5ln1Y":{"device":{"101":69,"102":4,"103":6,"104":61,"105":4},"os":{"1":1,"2":68,"4":39,"5":27,"10":1,"17":5,"19":2,"30":1}},"fOp1Fd1HB70":{"device":{"101":1},"os":{"2":1}},"ffi99h5QamA":{"device":{"102":2,"103":2,"104":1,"105":1},"os":{"5":2,"10":1,"12":2,"17":1}},"fuaj8_EMOFk":{"device":{"101":207,"102":21,"103":2,"104":84,"105":11},"os":{"1":3,"2":200,"4":59,"5":45,"9":3,"12":1,"17":2,"19":5,"26":1,"29":3,"30":2,"31":1}},"fvEclBQyoec":{"device":{"101":1},"os":{"2":1}},"fz-Tx6SW8pA":{"device":{"101":4,"102":1,"104":3},"os":{"1":1,"2":4,"4":3}},"g8A40NY4acw":{"device":{"101":1,"104":1},"os":{"2":1,"4":1}},"gACL9jyzAcE":{"device":{"101":534,"102":51,"103":10,"104":391,"105":49},"os":{"1":10,"2":517,"4":236,"5":214,"9":10,"10":6,"12":5,"17":2,"19":16,"21":2,"26":9,"27":2,"28":2,"29":3,"31":1}},"gDU5zPB2OF8":{"device":{"101":3,"104":3},"os":{"2":3,"4":1,"5":2}},"gE436H8C3VE":{"device":{"101":16,"102":2,"103":2,"104":8,"105":2},"os":{"1":3,"2":12,"4":7,"5":4,"9":1,"17":2,"26":1}},"gFGNQg0NtiU":{"device":{"101":3,"104":4},"os":{"2":3,"4":2,"5":2}},"gNZ6zFJciI4":{"device":{"101":21,"104":11},"os":{"1":1,"2":20,"4":6,"5":5}},"gRK3o2qCcsI":{"device":{"104":2},"os":{"4":2}},"ghVPea4maME":{"device":{"101":1},"os":{"2":1}},"gyy40GHxznk":{"device":{"101":2,"104":2},"os":{"2":2,"4":2}},"h1hq425flmw":{"device":{"101":1},"os":{"2":1}},"h7cQJ4tRkdE":{"device":{"104":2},"os":{"4":1,"5":1}},"hFGfHGyIlm8":{"device":{"101":6,"104":7,"105":6},"os":{"2":6,"4":10,"5":3}},"hKtccKQuNlc":{"device":{"104":2},"os":{"4":1,"5":1}},"hLKl4XVPXsw":{"device":{"101":2,"104":1},"os":{"2":2,"4":1}},"hMMxP6_YHbk":{"device":{"101":1,"104":7},"os":{"2":1,"4":1,"5":6}},"hZ2bgjMaWuY":{"device":{"100":1,"101":467,"102":154,"103":29,"104":791,"105":143},"os":{"1":25,"2":394,"4":491,"5":480,"9":49,"10":13,"12":31,"13":1,"17":14,"19":35,"21":4,"26":19,"27":2,"28":10,"29":9,"30":4,"31":4}},"he88SjSH0mE":{"device":{"104":6},"os":{"4":3,"5":3}},"hlCFtEFay7M":{"device":{"101":1,"104":3,"105":1},"os":{"5":4,"9":1}},"hqd8v6Aan4s":{"device":{"101":189,"102":50,"103":5,"104":174,"105":20},"os":{"1":13,"2":167,"4":131,"5":72,"9":12,"10":1,"12":3,"17":4,"19":20,"26":8,"28":2,"29":5}},"hrCsbxu8qH4":{"device":{"101":390,"102":56,"103":5,"104":187,"105":23},"os":{"1":9,"2":372,"4":159,"5":69,"9":6,"10":3,"12":4,"17":2,"19":12,"21":1,"26":7,"28":3,"29":10,"30":4}},"i-83UOiiHSI":{"device":{"101":2,"104":1},"os":{"2":2,"4":1}},"i0abkPM85A4":{"device":{"104":1},"os":{"5":1}},"i8v4pw53K-8":{"device":{"101":2},"os":{"2":2}},"iJ9KAW5omXc":{"device":{"101":2,"104":5,"105":2},"os":{"2":2,"4":4,"5":3}},"iLr_YGF8F-o":{"device":{"101":1},"os":{"2":1}},"iQJ26MzP-dU":{"device":{"101":2,"102":1,"104":2,"105":1},"os":{"2":2,"4":2,"5":1,"12":1}},"ilfGbDZCXMA":{"device":{"101":13,"102":2,"104":5},"os":{"1":1,"2":12,"4":5,"5":1,"26":1}},"iqJU0Zh9LXA":{"device":{"104":4,"105":1},"os":{"5":5}},"iuE-vx5Fk6U":{"device":{"101":2},"os":{"2":2}},"iye82MlKoIU":{"device":{"101":25,"102":9,"103":7,"104":56,"105":3},"os":{"1":3,"2":23,"4":37,"5":25,"9":2,"10":2,"12":1,"17":5,"19":1,"26":1}},"izvZFfEet5c":{"device":{"101":6,"102":1,"104":4,"105":1},"os":{"2":6,"4":3,"5":2,"26":1}},"j2rQgFRdhm4":{"device":{"101":4,"102":1,"103":1,"104":6},"os":{"2":4,"4":1,"5":5,"10":1,"29":1}},"j75YqjQiGEw":{"device":{"102":3},"os":{"26":3}},"jPxMIS2idxk":{"device":{"104":1},"os":{"5":1}},"jfUx10AMn0Y":{"device":{"101":56,"102":5,"103":2,"104":46,"105":2},"os":{"1":1,"2":52,"4":39,"5":11,"9":3,"10":1,"17":1,"19":1,"26":1,"29":1}},"jgZTl19hxhM":{"device":{"101":9,"103":1,"104":5},"os":{"2":8,"4":1,"5":4,"9":1,"17":1}},"jiGrj-STkMw":{"device":{"101":6,"102":2,"104":19,"105":3},"os":{"2":6,"4":12,"5":11,"26":1}},"jl3A_UIEnbs":{"device":{"101":25,"102":9,"103":3,"104":14,"105":6},"os":{"2":24,"4":17,"5":7,"10":2,"12":1,"17":1,"26":2,"29":2,"30":1}},"jqIEuFSXbCI":{"device":{"101":3,"104":2},"os":{"4":2,"9":3}},"jy0wF_4imv8":{"device":{"101":1,"104":2,"105":3},"os":{"2":1,"4":5}},"kAqCXPSwWfo":{"device":{"104":1},"os":{"5":1}},"kCo55n0hpiU":{"device":{"101":3,"104":8,"105":1},"os":{"2":3,"4":6,"5":3}},"kKmheCn0bTU":{"device":{"101":1,"102":2,"104":4},"os":{"1":1,"2":1,"4":2,"5":2,"26":1}},"kVsqGo7Sew0":{"device":{"101":6},"os":{"2":6}},"lJSADvshKRQ":{"device":{"101":92,"102":18,"103":6,"104":94,"105":13},"os":{"1":2,"2":78,"4":64,"5":51,"9":12,"10":5,"12":1,"17":1,"19":2,"21":2,"26":1,"28":2,"29":1,"30":1}},"lRSOcTl85SI":{"device":{"101":2,"102":1,"103":1,"104":7},"os":{"2":2,"4":6,"5":2,"17":1}},"lfMrcRb47qw":{"device":{"104":3},"os":{"5":3}},"ly7zKDh35V4":{"device":{"104":1},"os":{"5":1}},"m4HxYnNhTSA":{"device":{"101":1,"104":1},"os":{"5":1,"9":1}},"m8CQBAGYON4":{"device":{"101":4,"104":3},"os":{"2":4,"4":1,"5":2}},"mBtyntp0h-A":{"device":{"101":6,"102":2,"104":2},"os":{"2":6,"4":2,"26":1,"29":1}},"mFAa_tywOww":{"device":{"101":2},"os":{"2":1,"9":1}},"mKm7rBGWO3A":{"device":{"102":1,"103":2,"104":3},"os":{"4":2,"5":1,"10":1,"12":1,"17":1}},"mM9yNwIHTgI":{"device":{"101":10,"104":8},"os":{"1":1,"2":9,"4":7,"5":1}},"mS5tTCA0dB0":{"device":{"104":1},"os":{"4":1}},"maRI2WI9Ptc":{"device":{"101":17,"102":1,"103":1,"104":65,"105":4},"os":{"1":1,"2":12,"4":46,"5":23,"9":4,"17":1,"19":1}},"md1PH6d_Wr0":{"device":{"101":1,"103":1,"104":2},"os":{"2":1,"4":1,"5":1,"17":1}},"mxykcfi8tHk":{"device":{"101":86,"103":4,"104":50,"105":8},"os":{"1":1,"2":83,"4":41,"5":17,"9":2,"17":4}},"mzj9UOT33gE":{"device":{"101":1,"104":8},"os":{"2":1,"4":3,"5":5}},"nHw9fqsVhpk":{"device":{"101":4,"102":1,"103":2,"104":9,"105":2},"os":{"2":4,"4":7,"5":4,"10":2,"19":1}},"nInaxctSw7A":{"device":{"104":2},"os":{"4":2}},"nbE9MsgH1zQ":{"device":{"101":4,"104":1},"os":{"2":4,"5":1}},"nfplGZUSKR4":{"device":{"101":6,"102":5,"103":2,"104":13,"105":1},"os":{"2":6,"4":10,"5":5,"10":2,"26":1,"29":2,"31":1}},"nosJgOtAaGs":{"device":{"101":1},"os":{"2":1}},"oKtLrm0ogG0":{"device":{"101":3,"104":4},"os":{"2":3,"4":1,"5":3}},"oS4ot4lxGkA":{"device":{"101":4,"104":6},"os":{"2":4,"4":4,"5":2}},"ovt9tplYrc0":{"device":{"103":1},"os":{"10":1}},"p2ktK7QefSU":{"device":{"104":1},"os":{"5":1}},"pY0SQsn252Q":{"device":{"101":3,"103":1,"104":8},"os":{"2":3,"4":6,"5":2,"17":1}},"pcl5uVljLak":{"device":{"101":1},"os":{"2":1}},"ph8W9vb04sc":{"device":{"101":11,"102":3,"103":2,"104":12,"105":1},"os":{"1":1,"2":9,"4":6,"5":7,"9":1,"17":2,"19":1,"26":1,"29":1}},"pjNECZsShyw":{"device":{"101":7,"102":1,"104":17},"os":{"2":5,"4":8,"5":9,"9":2,"31":1}},"pv9mmWr0RaU":{"device":{"104":2},"os":{"5":2}},"pxFyOfqcu7M":{"device":{"101":12,"103":3,"104":7},"os":{"1":1,"2":9,"4":2,"5":5,"9":2,"10":2,"17":1}},"pzd7W_Zl_pw":{"device":{"101":90,"102":17,"103":3,"104":58,"105":7},"os":{"1":2,"2":82,"4":53,"5":17,"9":5,"10":3,"12":4,"19":2,"26":1,"28":1,"29":4,"30":1}},"q56usfyjaqk":{"device":{"101":7,"102":1,"103":1,"104":11},"os":{"1":1,"2":4,"4":5,"5":6,"9":1,"17":1,"19":1,"30":1}},"q8bK2JpEZuI":{"device":{"104":1},"os":{"4":1}},"qAEFtjIZTRU":{"device":{"101":22,"104":11},"os":{"2":22,"4":6,"5":5}},"qDd0rxiF6GI":{"device":{"101":115,"102":83,"103":43,"104":169,"105":21},"os":{"1":8,"2":103,"4":121,"5":85,"9":8,"10":19,"12":19,"17":24,"19":16,"26":14,"28":1,"29":10,"30":2,"31":1}},"qKSUtMT6P3s":{"device":{"101":1,"102":1,"103":2},"os":{"2":1,"17":2,"28":1}},"qU8hOWtn_H8":{"device":{"101":2,"102":2,"104":14},"os":{"2":2,"4":6,"5":8,"26":1,"29":1}},"qb76R-s8qj0":{"device":{"101":7,"102":2,"104":2,"105":1},"os":{"2":7,"4":4,"19":1}},"qhcKjsUrrJs":{"device":{"101":4,"102":2,"104":8},"os":{"2":4,"4":8,"19":1,"29":1}},"rfA50754lUk":{"device":{"101":4,"104":4},"os":{"2":4,"4":2,"5":2}},"roJS0yu2OhI":{"device":{"101":24,"103":1,"104":1},"os":{"2":24,"5":1,"10":1}},"ruGFyYyg4dk":{"device":{"101":196,"102":19,"103":3,"104":59,"105":6},"os":{"1":2,"2":192,"4":50,"5":27,"9":2,"10":1,"17":2,"19":3,"26":1,"29":3}},"rzh24aQrMD4":{"device":{"101":44,"102":2,"104":21,"105":2},"os":{"1":3,"2":40,"4":18,"5":5,"9":1,"19":2}},"s6qWEhmG4-4":{"device":{"101":31,"102":5,"103":4,"104":55,"105":10},"os":{"2":26,"4":44,"5":23,"9":5,"10":3,"12":1,"17":1,"19":1,"21":1}},"sCil2OvYJJ0":{"device":{"104":2},"os":{"4":2}},"sJ0dZDYHBuA":{"device":{"102":2,"104":1},"os":{"1":2,"4":1}},"scfiJdkXZsA":{"device":{"101":1,"104":4},"os":{"2":1,"4":4}},"sfXrh2EL-zk":{"device":{"104":2},"os":{"4":2}},"spubr4ivl3s":{"device":{"104":2},"os":{"4":2}},"sxS3it1JTXo":{"device":{"101":1,"104":1},"os":{"2":1,"4":1}},"t-Mp471p2oE":{"device":{"101":2,"102":17,"103":2,"104":19,"105":1},"os":{"1":3,"2":2,"4":12,"5":8,"12":3,"17":2,"19":8,"26":2,"29":1}},"t4ZAt0KmMjQ":{"device":{"101":13,"104":21,"105":1},"os":{"1":1,"2":12,"4":15,"5":7}},"t7C5-A_Rp-s":{"device":{"101":12,"102":1,"103":2,"104":8,"105":4},"os":{"2":12,"4":9,"5":3,"10":1,"12":1,"17":1}},"tA502VldXkw":{"device":{"101":1},"os":{"2":1}},"tOB5pl_CJOI":{"device":{"104":3},"os":{"4":3}},"tXsysReyjkw":{"device":{"101":4,"103":2,"104":3,"105":1},"os":{"2":2,"5":4,"9":2,"17":2}},"tdfe8pM-P1E":{"device":{"101":3,"104":2,"105":1},"os":{"1":1,"2":2,"4":3}},"tirJkYSXZvI":{"device":{"101":10,"104":24},"os":{"2":9,"4":10,"5":14,"9":1}},"tjRdSwIgoWM":{"device":{"101":1,"104":1},"os":{"5":1,"9":1}},"tu1tn2IIGK8":{"device":{"101":1,"103":1,"104":12},"os":{"2":1,"4":8,"5":4,"17":1}},"tzZMmdAu0fM":{"device":{"102":1,"104":1},"os":{"4":1,"12":1}},"tzZPHiV_F8I":{"device":{"101":1,"104":6,"105":1},"os":{"2":1,"4":2,"5":5}},"u7I67LdUZVw":{"device":{"101":7,"104":7},"os":{"2":7,"4":4,"5":3}},"uE4RYCazSsU":{"device":{"104":1},"os":{"4":1}},"uKpMlqA7row":{"device":{"101":17,"102":5,"104":8,"105":1},"os":{"2":16,"4":5,"5":4,"9":1,"12":3,"19":2}},"uLcvlK77WPM":{"device":{"101":98,"104":17,"105":2},"os":{"2":96,"4":12,"5":7,"9":2}},"uYPiiqm_oTU":{"device":{"101":5,"102":1,"104":14},"os":{"1":1,"2":4,"4":8,"5":6,"9":1}},"uZDU-fj7d1o":{"device":{"105":1},"os":{"4":1}},"uZwUrAQmtKo":{"device":{"101":7,"103":2,"104":3,"105":2},"os":{"2":7,"4":3,"5":2,"17":2}},"ux4SvDUqi3w":{"device":{"104":1},"os":{"5":1}},"v36bDCp_a9o":{"device":{"101":1},"os":{"2":1}},"v8XxYlnhfiQ":{"device":{"101":4,"104":4},"os":{"2":4,"4":1,"5":3}},"vOPK8X8bKPU":{"device":{"101":2,"102":1,"104":1},"os":{"2":2,"4":1,"29":1}},"vijhffP1FUY":{"device":{"103":1,"104":1},"os":{"4":1,"10":1}},"vvANTzn-0Nw":{"device":{"101":2,"104":1},"os":{"2":2,"5":1}},"w3CutQDzymI":{"device":{"101":6,"102":1,"104":5,"105":1},"os":{"2":6,"4":5,"5":1,"19":1}},"wHkQIamN-To":{"device":{"102":1,"104":7},"os":{"4":5,"5":3}},"wJSf-j-nIdQ":{"device":{"101":1,"102":2,"104":2,"105":2},"os":{"2":1,"4":3,"5":1,"12":1,"26":1}},"wV2sedXUfKo":{"device":{"104":10},"os":{"4":5,"5":5}},"wb5qzEdLTyU":{"device":{"101":6,"104":11},"os":{"1":1,"2":5,"4":6,"5":5}},"wl3UoSq2C1Y":{"device":{"101":4},"os":{"1":1,"2":3}},"xFR-iPa6-FY":{"device":{"101":1,"105":1},"os":{"2":1,"4":1}},"xKoRmr56LOU":{"device":{"101":3,"104":1},"os":{"2":3,"4":1}},"xKrXUNpDAXI":{"device":{"101":3},"os":{"2":3}},"xKy4e8afJUM":{"device":{"101":9,"102":1,"104":3,"105":1},"os":{"1":1,"2":6,"4":4,"9":2,"26":1}},"xM1u1pUhznI":{"device":{"101":1,"104":2},"os":{"2":1,"4":2}},"xkvlfY-icXM":{"device":{"101":2,"104":2},"os":{"2":2,"5":2}},"xlsRk2WlkI4":{"device":{"101":4,"103":1,"104":9,"105":2},"os":{"2":4,"4":8,"5":3,"10":1}},"ydfF5_M0B4E":{"device":{"101":2},"os":{"2":2}},"z3aFxD7iUSY":{"device":{"100":3,"101":205,"102":56,"103":27,"104":157,"105":30},"os":{"1":17,"2":176,"4":142,"5":50,"9":19,"10":11,"12":8,"17":16,"19":18,"21":3,"26":3,"28":1,"29":9,"30":5}},"z5ujpf1wgGA":{"device":{"101":15,"102":10,"103":4,"104":37,"105":12},"os":{"2":15,"4":35,"5":18,"10":1,"12":1,"17":2,"19":3,"26":1,"27":1,"31":1}},"z7Pm39VM8-0":{"device":{"101":29,"102":9,"103":7,"104":91,"105":7},"os":{"2":26,"4":61,"5":43,"9":3,"10":2,"12":1,"17":5,"19":1,"29":1}},"zI2tl261ap4":{"device":{"101":3,"104":1},"os":{"2":3,"4":1}},"zME3FgQBF_s":{"device":{"101":1,"104":1},"os":{"2":1,"4":1}},"zRUrDjUVc2E":{"device":{"101":31,"102":3,"104":16,"105":3},"os":{"1":2,"2":26,"4":12,"5":7,"9":4,"19":1,"29":1}},"zXNud28NB20":{"device":{"104":1},"os":{"5":1}},"z_jIz8j5_sg":{"device":{"101":8,"102":3,"104":10,"105":2},"os":{"2":8,"4":10,"5":2,"12":1,"19":1,"26":1}},"znlfqiV5tLU":{"device":{"101":2,"104":5},"os":{"2":1,"4":5,"9":1}},"zwu1_ldtVq4":{"device":{"101":1},"os":{"2":1}}}},"generated_at":"2026-07-24T11:26:20.464283+00:00","last_90d":{"channel":{"device":{"100":11,"101":12701,"102":1762,"103":751,"104":13511,"105":1377},"os":{"1":429,"2":11678,"4":8908,"5":6403,"9":638,"10":358,"12":225,"13":6,"17":378,"19":432,"21":36,"22":2,"26":254,"27":15,"28":61,"29":175,"30":86,"31":29}},"videos":{"-3EjJEa_9FY":{"device":{"101":1,"104":2},"os":{"2":1,"4":2}},"-9wEv6t9EUM":{"device":{"101":5,"104":3},"os":{"2":5,"4":1,"5":2}},"-dJ8qzKSMEI":{"device":{"101":12,"102":2,"104":4},"os":{"2":12,"4":3,"5":1,"26":1,"29":1}},"-nfSZAxrKeE":{"device":{"101":1,"102":3,"104":3,"105":2},"os":{"2":1,"4":2,"5":3,"19":2,"29":1}},"-wi95pfC39s":{"device":{"101":6,"104":5},"os":{"2":6,"4":2,"5":3}},"00LZPcwzJVU":{"device":{"101":1,"104":7},"os":{"2":1,"4":6,"5":1}},"0CwqSvbb_gg":{"device":{"100":1,"101":36,"102":1,"103":2,"104":45},"os":{"1":2,"2":35,"4":21,"5":24,"9":1,"10":2}},"0HefYbtHZvU":{"device":{"101":3},"os":{"2":3}},"0L7OJ2Y44WE":{"device":{"101":2,"102":4,"103":5,"104":4,"105":4},"os":{"2":2,"4":6,"5":2,"10":5,"12":1,"19":1,"26":2}},"115HiW_eJJs":{"device":{"105":2},"os":{"4":2}},"1HO0aEv_Tzc":{"device":{"101":35,"102":3,"104":22,"105":3},"os":{"1":1,"2":35,"4":17,"5":8,"19":1,"29":1}},"1J6rolJBREU":{"device":{"101":1,"102":1,"104":1},"os":{"5":1,"9":1,"12":1}},"1LfsXaLm_P0":{"device":{"104":2},"os":{"4":2}},"1k2xQeGTTHs":{"device":{"104":2},"os":{"4":2}},"1vXOHKdcX7o":{"device":{"101":1,"103":1,"104":3,"105":1},"os":{"2":1,"4":2,"5":2,"10":1}},"23hyqJp9-lE":{"device":{"101":16,"104":10},"os":{"2":12,"4":8,"5":2,"9":4}},"26f_oIZH6ug":{"device":{"104":1},"os":{"4":1}},"26ftkHABnVg":{"device":{"101":12,"104":36,"105":2},"os":{"1":1,"2":8,"4":13,"5":25,"9":2,"30":1}},"2Cve8HMD3r4":{"device":{"101":6,"103":1,"104":5,"105":1},"os":{"2":6,"4":2,"5":4,"17":1}},"2XkcnarPcfs":{"device":{"104":10,"105":5},"os":{"4":15}},"2gZvSk6btFc":{"device":{"101":168,"102":16,"103":1,"104":63,"105":12},"os":{"1":5,"2":155,"4":56,"5":25,"9":7,"12":2,"17":1,"19":3,"26":2,"29":3,"30":1}},"2nsgqcGrp6s":{"device":{"101":1,"103":1,"104":10,"105":1},"os":{"2":1,"4":6,"5":5,"10":1}},"3-S2Whrzitw":{"device":{"101":3,"103":3,"104":6,"105":1},"os":{"2":1,"4":2,"5":5,"9":2,"10":3}},"38PxRLbK55U":{"device":{"101":9,"102":1,"103":1,"104":6},"os":{"1":1,"2":8,"4":5,"5":1,"17":1,"19":1}},"3ByYahv-7BA":{"device":{"101":138,"102":1,"104":52},"os":{"1":2,"2":134,"4":26,"5":26,"9":2,"29":1}},"3CZZ47LWegk":{"device":{"101":1},"os":{"2":1}},"3DVZS29lVv0":{"device":{"102":1,"103":1,"104":9},"os":{"1":1,"4":5,"5":4,"17":1}},"3GYBR2-GuzU":{"device":{"104":1},"os":{"4":1}},"3PHRIerzzIw":{"device":{"101":1,"104":10},"os":{"2":1,"4":6,"5":4}},"3Qoxr0RZPbA":{"device":{"101":1,"104":1},"os":{"4":1,"9":1}},"3YjbU1TjcPQ":{"device":{"101":2,"104":5},"os":{"2":2,"4":5}},"3lEBobiGGiw":{"device":{"101":44,"104":2,"105":1},"os":{"2":40,"4":1,"5":2,"9":4}},"4-X8kYgDNII":{"device":{"101":2,"104":2},"os":{"2":2,"5":2}},"47dWPH0gK8Q":{"device":{"101":11,"104":22},"os":{"1":1,"2":10,"4":11,"5":11}},"4AWSe96znVs":{"device":{"101":3,"102":1,"103":1,"104":3,"105":1},"os":{"2":3,"4":2,"5":2,"17":1,"19":1}},"4Bly1zF66L8":{"device":{"101":1,"103":3,"104":9,"105":3},"os":{"2":1,"4":5,"5":7,"10":1,"17":2}},"4MFGQA5mNoQ":{"device":{"101":19,"102":4,"104":16,"105":1},"os":{"2":18,"4":9,"5":8,"9":1,"26":4}},"4RBo2WhsWGY":{"device":{"101":2,"102":1,"103":3,"104":7,"105":2},"os":{"2":1,"4":5,"5":4,"9":1,"10":3,"26":1}},"4RYKHoKMjC4":{"device":{"101":5,"104":23},"os":{"2":5,"4":14,"5":9}},"4VHQaw2nRSk":{"device":{"101":4},"os":{"2":4}},"4owwPSS1SdM":{"device":{"101":3,"104":1},"os":{"2":2,"5":1,"9":1}},"4qYYWH2Km4g":{"device":{"104":3},"os":{"5":3}},"4uzwSeHNyFk":{"device":{"101":7,"102":2,"104":8},"os":{"2":7,"4":2,"5":6,"19":2}},"50_H0j9eEto":{"device":{"101":1,"104":3},"os":{"2":1,"4":1,"5":2}},"561WFdai_mI":{"device":{"104":1},"os":{"4":1}},"5Bu7AhTvSfU":{"device":{"101":1,"102":1,"104":4},"os":{"2":1,"4":4,"19":1}},"5Ntxn2faXt8":{"device":{"101":3033,"102":31,"103":8,"104":1323,"105":67},"os":{"1":41,"2":2966,"4":636,"5":761,"9":27,"10":4,"13":2,"17":4,"19":9,"26":4,"28":1,"29":2,"30":4,"31":1}},"5Q_rZzh8NrE":{"device":{"101":2},"os":{"2":2}},"5Qc0KQiy_9Q":{"device":{"104":3},"os":{"4":2,"5":1}},"5RGZweasTWs":{"device":{"102":1,"104":3},"os":{"4":3,"26":1}},"5Y3EsWmOPZM":{"device":{"101":101,"102":30,"103":10,"104":110,"105":22},"os":{"1":6,"2":88,"4":90,"5":50,"9":6,"10":8,"12":4,"13":1,"17":2,"19":6,"21":1,"26":2,"28":4,"30":4,"31":1}},"5ahyyMboTbE":{"device":{"101":145,"102":67,"103":49,"104":199,"105":41},"os":{"1":11,"2":124,"4":176,"5":78,"9":15,"10":23,"12":7,"17":26,"19":17,"21":4,"26":9,"28":1,"29":8,"30":1,"31":1}},"5dDwVcJT7tA":{"device":{"104":1},"os":{"5":1}},"5jcApdKyZ-I":{"device":{"101":2},"os":{"2":2}},"5nGSY6YxMBE":{"device":{"101":2,"102":1,"103":1,"104":11},"os":{"2":2,"4":7,"5":4,"17":1,"19":1}},"5w4RjcxqV-o":{"device":{"101":195,"102":47,"103":23,"104":159,"105":23},"os":{"1":14,"2":165,"4":124,"5":67,"9":18,"10":1,"12":7,"13":1,"17":22,"19":4,"26":10,"28":4,"29":4,"30":2,"31":4}},"5wnZYrZ2ZvI":{"device":{"101":28,"102":4,"103":33,"104":71,"105":4},"os":{"2":26,"4":50,"5":26,"9":2,"10":32,"12":1,"17":1,"26":1,"28":1}},"67ifyj_oxYQ":{"device":{"101":2,"102":1},"os":{"2":2,"19":1}},"6Ch39rrY2PY":{"device":{"101":40,"104":15},"os":{"2":39,"4":5,"5":10,"9":1}},"6Nj6vwLk3rM":{"device":{"104":3},"os":{"4":3}},"6ShaabGAA1I":{"device":{"101":164,"102":27,"103":14,"104":187,"105":9},"os":{"1":5,"2":147,"4":139,"5":64,"9":13,"10":3,"12":4,"17":11,"19":5,"22":1,"26":3,"28":2,"29":1,"31":3}},"6b4QUPNjG00":{"device":{"101":1},"os":{"2":1}},"7-Rftp6KFn8":{"device":{"101":5,"104":1},"os":{"2":5,"5":1}},"756xyJRy2T4":{"device":{"101":9,"104":2},"os":{"2":7,"4":1,"5":1,"9":2}},"7Ez-74SuHZ8":{"device":{"101":59,"102":1,"104":7},"os":{"1":2,"2":55,"4":5,"5":2,"9":2,"12":1}},"7f9k1ruyX54":{"device":{"101":2,"104":4},"os":{"2":2,"4":2,"5":2}},"7lHQ-KfpY2o":{"device":{"101":118,"102":77,"103":32,"104":376,"105":43},"os":{"1":8,"2":99,"4":356,"5":83,"9":12,"10":13,"12":8,"13":1,"17":18,"19":16,"26":15,"27":1,"28":3,"29":12,"30":1}},"7mXcpZKG_18":{"device":{"104":1},"os":{"4":1}},"7sYn3ZCAhKg":{"device":{"101":1},"os":{"2":1}},"7u5OzzRKiA4":{"device":{"105":1},"os":{"4":1}},"7yIZo3YBxYo":{"device":{"101":12,"102":2,"103":1,"104":11,"105":4},"os":{"2":6,"4":9,"5":6,"9":6,"10":1,"19":1,"26":1}},"82A8enPYdZE":{"device":{"101":1},"os":{"2":1}},"8GdD4czvJro":{"device":{"101":34,"102":13,"103":1,"104":64,"105":5},"os":{"1":14,"2":19,"4":63,"5":14,"9":1,"12":1,"17":1,"26":2,"28":2}},"8WX54HD_LOs":{"device":{"101":1,"103":1,"104":3,"105":1},"os":{"2":1,"4":2,"5":2,"17":1}},"8w-FuJNlm-o":{"device":{"101":189,"102":13,"103":1,"104":523,"105":47},"os":{"1":1,"2":171,"4":358,"5":217,"9":13,"10":1,"12":2,"19":3,"26":2,"30":4,"31":1}},"9Dcery3yjBo":{"device":{"101":7,"102":1,"104":56,"105":2},"os":{"2":6,"4":31,"5":27,"9":1,"29":1}},"9JxwIbZ412g":{"device":{"101":2},"os":{"2":2}},"9ODh2yjrCPA":{"device":{"101":6,"102":7,"103":2,"104":15,"105":7},"os":{"2":4,"4":14,"5":10,"10":1,"12":1,"17":1,"19":2,"26":1,"29":1,"30":2}},"9Yam9_xQJI8":{"device":{"101":149,"102":20,"103":11,"104":178,"105":22},"os":{"1":7,"2":129,"4":109,"5":96,"9":11,"10":6,"12":6,"17":5,"19":4,"26":1,"29":2,"30":3,"31":1}},"A-ab2t50WUY":{"device":{"101":13,"102":6,"103":3,"104":13,"105":4},"os":{"2":13,"4":10,"5":9,"10":2,"17":1,"19":1,"26":2,"29":1}},"A9hK0en2Uqg":{"device":{"101":3,"104":4},"os":{"2":3,"4":2,"5":2}},"AAX9HV6mOCg":{"device":{"101":2,"104":1},"os":{"2":2,"4":1}},"ABBnd9c6ImI":{"device":{"104":1},"os":{"5":1}},"AJ_fphmB848":{"device":{"101":1},"os":{"2":1}},"AQdnbOgM71k":{"device":{"101":483,"102":32,"103":6,"104":416,"105":57},"os":{"1":6,"2":462,"4":264,"5":212,"9":13,"10":2,"12":4,"17":3,"19":13,"26":8,"27":1,"29":2,"30":4}},"AaejCpNADp8":{"device":{"101":1,"103":3,"104":3,"105":2},"os":{"2":1,"4":3,"5":2,"10":3}},"AvcVvsrk8dE":{"device":{"101":14,"104":7},"os":{"2":13,"4":6,"5":1,"9":1}},"B5--JAJjyw8":{"device":{"101":5},"os":{"2":5}},"BHHckNXaeRI":{"device":{"104":3},"os":{"4":1,"5":2}},"BI2u1YDcrdM":{"device":{"101":1,"104":2,"105":1},"os":{"4":1,"5":2,"30":1}},"BKMv6AxH5CI":{"device":{"101":1},"os":{"30":1}},"BMIcOvi0w20":{"device":{"104":1},"os":{"4":1}},"BRUSFtx-H3U":{"device":{"101":3,"102":3,"103":1,"104":4,"105":2},"os":{"1":1,"2":3,"4":3,"5":3,"10":1,"12":2}},"BcOZT21IDGI":{"device":{"101":1,"104":2},"os":{"2":1,"4":2}},"Be_-4zjAbc0":{"device":{"101":24,"102":8,"103":14,"104":49,"105":6},"os":{"1":1,"2":23,"4":28,"5":28,"9":1,"10":4,"17":10,"19":4,"26":1,"29":1}},"BvFP14yAD8I":{"device":{"101":1},"os":{"2":1}},"ByYu9JrTDrQ":{"device":{"101":5,"102":1,"103":1,"104":1},"os":{"2":5,"5":1,"12":1,"17":1}},"C91-OR-s-UY":{"device":{"101":1,"104":2},"os":{"2":1,"4":2}},"CCjPVVUO0MY":{"device":{"101":5,"102":1,"104":3},"os":{"2":4,"4":1,"5":2,"9":1,"19":1}},"CD_z7fOmZYE":{"device":{"101":4,"104":3},"os":{"1":1,"2":2,"4":2,"5":1,"9":1}},"CajKQ01dCP0":{"device":{"104":1},"os":{"4":1}},"CdlWvITC8qw":{"device":{"100":2,"101":84,"102":15,"103":4,"104":73,"105":8},"os":{"1":3,"2":83,"4":55,"5":26,"9":1,"10":1,"12":3,"17":3,"19":8,"21":1,"29":2}},"Cq-Ajxe2Jo8":{"device":{"101":4,"104":2},"os":{"2":4,"4":1,"5":1}},"Crkib9LfwEM":{"device":{"101":1,"103":1,"104":3},"os":{"2":1,"4":3,"17":1}},"D42bM3u0InI":{"device":{"101":18,"102":7,"104":18,"105":1},"os":{"1":3,"2":13,"4":14,"5":6,"9":5,"12":1,"19":1,"26":1}},"DYg4XrwkM9Q":{"device":{"101":4,"103":1,"104":7,"105":1},"os":{"2":4,"4":4,"5":4,"17":1}},"Df-Sfz_vLJ4":{"device":{"101":1,"104":2},"os":{"2":1,"4":1,"5":1}},"DobDHytF5OY":{"device":{"101":1},"os":{"2":1}},"DvA1ZefR7wQ":{"device":{"101":1},"os":{"9":1}},"E3zJyj3RYR4":{"device":{"101":2,"102":1,"104":3},"os":{"2":2,"4":1,"5":2,"19":1}},"E61VDhCxwWI":{"device":{"101":39,"102":11,"103":22,"104":314,"105":30},"os":{"1":2,"2":33,"4":131,"5":217,"9":2,"10":17,"17":5,"19":5,"29":2,"30":2}},"EEjJhrqkrvo":{"device":{"101":1,"102":1,"104":5},"os":{"4":5,"9":1,"12":1}},"EVSDFA42HPE":{"device":{"102":1},"os":{"19":1}},"EePeG9dDG8c":{"device":{"101":5,"102":1,"103":1,"104":17,"105":1},"os":{"2":5,"4":17,"5":2,"27":1}},"EkAM7FFAIZs":{"device":{"101":4},"os":{"2":4}},"EmKTi4GAj1s":{"device":{"102":1,"104":9},"os":{"4":5,"5":4,"19":1}},"F3l2CZE3-_0":{"device":{"104":1},"os":{"5":1}},"F7KGvcgEMj8":{"device":{"101":5,"104":14,"105":1},"os":{"2":4,"4":7,"5":8,"9":1}},"FAu1ag2mC_4":{"device":{"104":2},"os":{"4":2}},"FKDVSeBD_IQ":{"device":{"101":1},"os":{"2":1}},"FPYjEhH5Viw":{"device":{"104":6,"105":2},"os":{"4":8}},"FQhNwkGPrtU":{"device":{"101":2},"os":{"2":2}},"FiUedyH1fVk":{"device":{"102":1},"os":{"4":1}},"FxxONV7QhiA":{"device":{"104":3},"os":{"4":3}},"FzOTKEQZ-hY":{"device":{"101":1,"104":1},"os":{"2":1,"4":1}},"GMFAiPaUbLA":{"device":{"101":35,"104":19},"os":{"1":1,"2":34,"4":10,"5":9}},"GPENFuAFawI":{"device":{"102":1,"103":1,"104":4},"os":{"4":3,"5":1,"10":1,"31":1}},"GTVYSV1oE2E":{"device":{"101":3,"104":3},"os":{"2":3,"4":1,"5":2}},"GbXE9PAzXRI":{"device":{"101":4,"104":4},"os":{"2":2,"4":2,"5":2,"9":2}},"Gca1yHItwd0":{"device":{"101":7,"104":3},"os":{"2":7,"4":3}},"GsjT4T6B_S8":{"device":{"104":4},"os":{"4":4}},"GvmXD9ia4I8":{"device":{"101":89,"102":14,"104":36,"105":4},"os":{"2":81,"4":25,"5":18,"9":8,"12":2,"19":4,"26":2,"28":1,"29":1,"31":1}},"GxMsyWHTR1c":{"device":{"101":1,"104":1,"105":2},"os":{"2":1,"4":2,"5":1}},"HAy1IwAn1O0":{"device":{"101":126,"102":16,"103":8,"104":65,"105":8},"os":{"1":8,"2":114,"4":46,"5":33,"9":6,"10":5,"12":2,"17":3,"19":3,"28":1,"29":2}},"HGZCTzDL01w":{"device":{"103":1},"os":{"10":1}},"Hdy822qo8lA":{"device":{"104":2},"os":{"4":1,"5":1}},"I0WsADNO_mc":{"device":{"101":188,"102":3,"104":108,"105":5},"os":{"1":1,"2":185,"4":59,"5":55,"9":2,"12":1,"26":1}},"I28qtymZsGQ":{"device":{"102":1},"os":{"1":1}},"I4GB0wucViM":{"device":{"101":4,"105":1},"os":{"2":2,"5":1,"9":2}},"ICTJOHPa1Ag":{"device":{"101":35,"102":1,"104":44,"105":5},"os":{"1":1,"2":29,"4":29,"5":21,"9":5}},"IJiDnjh5k28":{"device":{"101":4,"104":1},"os":{"2":4,"4":1}},"IOwa_0n1dHE":{"device":{"101":12,"102":2,"104":14,"105":3},"os":{"2":10,"4":10,"5":7,"9":1,"12":1,"19":1,"30":1}},"Ictg8L25QM8":{"device":{"102":1,"104":5},"os":{"4":3,"5":3}},"Iui1Q86fRDo":{"device":{"101":5,"104":3},"os":{"2":5,"4":2,"5":1}},"J4hpbb9rRCg":{"device":{"101":4,"104":2},"os":{"2":4,"4":2}},"JP11PpfEHAk":{"device":{"101":1,"105":1},"os":{"2":1,"4":1}},"JUNpp3T0T2Q":{"device":{"101":29,"102":2,"103":2,"104":75,"105":2},"os":{"1":5,"2":25,"4":49,"5":28,"10":2,"19":1}},"J_vdKLo9aYE":{"device":{"101":1},"os":{"2":1}},"JgXeYJrYP3Y":{"device":{"101":1},"os":{"2":1}},"JhIFjQPsEGo":{"device":{"104":3},"os":{"4":2,"5":1}},"JjTSfJy26oI":{"device":{"101":34,"104":6},"os":{"1":2,"2":32,"4":5,"5":1}},"JkKpxFUiOPQ":{"device":{"101":25,"104":5},"os":{"2":25,"4":4,"5":1}},"Jwjfz6CAF1U":{"device":{"101":3,"104":1},"os":{"2":3,"4":1}},"K1-1W4cDC8w":{"device":{"101":1,"104":1},"os":{"2":1,"4":1}},"K21tmxGSg1c":{"device":{"101":15,"102":1,"103":3,"104":17,"105":2},"os":{"2":15,"4":8,"5":11,"10":2,"17":1,"26":1}},"KBhT3_S-Wyc":{"device":{"101":7,"102":1,"103":1,"104":12},"os":{"2":7,"4":8,"5":4,"17":1,"26":1}},"KXx7-M3EAIY":{"device":{"101":5,"104":2},"os":{"2":5,"4":2}},"Kb1o7hXJvv4":{"device":{"101":44,"102":13,"103":5,"104":52,"105":13},"os":{"1":2,"2":42,"4":45,"5":24,"10":4,"17":1,"19":2,"26":3,"29":3,"30":1}},"Kc5LB_Kf5iQ":{"device":{"104":4},"os":{"4":3,"5":1}},"KlAgm3lGFFQ":{"device":{"101":5,"102":3,"104":5,"105":1},"os":{"2":5,"4":5,"5":2,"26":2}},"Kxt1oWOgvoI":{"device":{"101":110,"102":15,"104":52,"105":12},"os":{"1":8,"2":95,"4":43,"5":24,"9":8,"12":1,"19":6,"26":2,"31":2}},"L8W_tyWswvQ":{"device":{"101":5,"102":4,"103":1,"104":11,"105":1},"os":{"1":1,"2":4,"4":6,"5":6,"9":1,"17":1,"26":3}},"LANgtT8CJHU":{"device":{"101":11,"103":2,"104":13},"os":{"2":8,"4":11,"5":2,"9":3,"10":2}},"LPsOL4MCO5A":{"device":{"101":3,"102":2,"104":3},"os":{"2":3,"4":3,"12":1,"26":1}},"LRnNHhWu2eA":{"device":{"101":1},"os":{"2":1}},"LherFWJgr9M":{"device":{"101":4,"102":4,"103":1,"104":6,"105":2},"os":{"2":4,"4":3,"5":5,"10":1,"21":1,"26":1,"29":2}},"LzkQPjzP--E":{"device":{"104":2},"os":{"4":2}},"MLxe1ridlRY":{"device":{"101":4,"104":1},"os":{"2":4,"4":1}},"MMunBaTQL64":{"device":{"101":13,"102":1,"103":2,"104":88,"105":4},"os":{"1":1,"2":9,"4":46,"5":46,"9":3,"10":1,"17":1,"28":1}},"MOrj_qRc3zQ":{"device":{"101":1},"os":{"2":1}},"MXrhaajx594":{"device":{"101":11,"102":21,"103":4,"104":31,"105":7},"os":{"2":11,"4":32,"5":13,"10":3,"17":1,"19":3,"21":11}},"MlzPM8jR0Gk":{"device":{"100":1,"101":11},"os":{"1":1,"2":11}},"NYgA50vM9-Y":{"device":{"101":7,"104":6},"os":{"2":7,"4":4,"5":2}},"Nq3FE46itYg":{"device":{"101":40,"104":6,"105":1},"os":{"1":1,"2":38,"4":5,"5":2,"9":1}},"Nr_298OOamA":{"device":{"102":3,"104":1},"os":{"4":1,"19":3}},"NzdorOVDlw0":{"device":{"101":13,"102":1,"104":13},"os":{"1":1,"2":11,"4":5,"5":9,"9":1}},"O668BaDTXIo":{"device":{"101":1},"os":{"2":1}},"OCenVqWNt7g":{"device":{"104":3},"os":{"4":1,"5":2}},"OHT33Pv7Du0":{"device":{"101":1},"os":{"2":1}},"OJnD6iCI1yM":{"device":{"100":1,"101":32,"104":23,"105":2},"os":{"1":2,"2":30,"4":21,"5":4,"9":1}},"OOoyvAq-s2Y":{"device":{"101":1,"104":1},"os":{"2":1,"4":1}},"Ob8GV-84B8o":{"device":{"104":1},"os":{"5":1}},"OopDjsg19UQ":{"device":{"101":21,"102":7,"103":12,"104":36,"105":7},"os":{"1":1,"2":19,"4":24,"5":19,"9":2,"10":6,"17":6,"19":2,"26":1,"28":1,"29":2}},"P2iT1TUoklM":{"device":{"101":1},"os":{"2":1}},"P6yTTTqGmT0":{"device":{"101":18,"102":4,"103":1,"104":65,"105":4},"os":{"2":16,"4":54,"5":18,"9":2,"10":1,"19":1}},"P7g39CZtRRg":{"device":{"104":1},"os":{"4":1}},"PNjiwlnZ3Lc":{"device":{"104":4},"os":{"4":1,"5":3}},"Pb-4FMXIz40":{"device":{"101":9,"102":9,"103":3,"104":51,"105":2},"os":{"1":1,"2":8,"4":35,"5":22,"9":1,"10":1,"17":2,"26":4}},"PbbfmaZ4JxY":{"device":{"101":5,"104":2},"os":{"2":4,"5":2,"9":1}},"PhsQA0sYjsc":{"device":{"101":20,"104":3},"os":{"2":20,"4":3}},"PtZsi7HFsKk":{"device":{"101":4,"102":1,"104":4},"os":{"2":4,"4":4,"28":1}},"Q0BZe9WN1y8":{"device":{"101":34,"102":8,"103":4,"104":82,"105":8},"os":{"1":4,"2":29,"4":54,"5":40,"9":1,"10":1,"12":2,"17":3,"26":1,"29":1}},"Q77jfi8FAC0":{"device":{"101":20,"102":3,"104":8},"os":{"2":16,"4":8,"5":1,"9":4,"19":2}},"Q9M_HL1L9fs":{"device":{"101":2,"104":1},"os":{"2":2,"5":1}},"QNiLsEGVV0k":{"device":{"101":10,"104":5},"os":{"2":10,"5":5}},"Q_WB-lnyyIo":{"device":{"101":29,"102":2,"103":1,"104":17,"105":4},"os":{"1":1,"2":27,"4":15,"5":7,"9":1,"17":1,"26":1}},"QbZ1hsNMdkU":{"device":{"101":1},"os":{"2":1}},"QeOeqfvlbbg":{"device":{"101":4,"102":2,"104":5},"os":{"2":1,"4":4,"5":1,"9":3,"19":1,"29":1}},"QuPSPzhEJJU":{"device":{"101":21,"102":3,"103":5,"104":16},"os":{"1":2,"2":18,"4":11,"5":5,"9":1,"10":2,"17":3,"19":1,"26":1,"29":1}},"R-64MF2ooWw":{"device":{"104":4},"os":{"4":2,"5":2}},"RBLcszExDvQ":{"device":{"104":1},"os":{"4":1}},"RCUWuigh49Q":{"device":{"101":21,"102":3,"103":5,"104":28,"105":6},"os":{"1":1,"2":20,"4":21,"5":15,"10":1,"17":4,"19":1}},"RRh-oOwZ_s0":{"device":{"101":1},"os":{"2":1}},"RV4K2ErGgA0":{"device":{"101":3,"104":2,"105":1},"os":{"1":1,"2":1,"4":1,"5":2,"9":1}},"RZEvZAC-ybA":{"device":{"101":1,"102":1},"os":{"2":1,"19":1}},"RfTqo8_Brbg":{"device":{"101":5,"103":1,"104":4},"os":{"2":5,"4":2,"5":2,"17":1}},"RhcLtnEWDfU":{"device":{"101":11,"104":5,"105":2},"os":{"1":6,"2":5,"4":7}},"RjoE7uPjobs":{"device":{"101":2,"103":2,"104":4,"105":1},"os":{"2":2,"4":3,"5":2,"10":2}},"RufIydXWWmo":{"device":{"101":69,"102":1,"103":5,"104":131,"105":5},"os":{"1":1,"2":67,"4":60,"5":76,"9":1,"17":5,"19":1}},"SBJV7VwLnbM":{"device":{"101":9,"104":2},"os":{"2":9,"4":1,"5":1}},"SE667oAdPGI":{"device":{"101":7,"102":4,"104":2,"105":4},"os":{"2":7,"4":5,"5":1,"19":1,"26":3}},"SFj5gcK_R1g":{"device":{"103":1,"104":1},"os":{"5":1,"10":1}},"SPXWj18a4TM":{"device":{"104":8},"os":{"4":1,"5":7}},"SR7dLH10Eh4":{"device":{"101":1,"104":3},"os":{"2":1,"5":3}},"SY7dJkwvZ8Q":{"device":{"101":5,"104":3},"os":{"2":4,"4":1,"5":2,"9":1}},"SgKD1JbYsgg":{"device":{"105":1},"os":{"4":1}},"SiGTsE2CctY":{"device":{"101":39,"102":13,"104":19,"105":2},"os":{"1":3,"2":31,"4":19,"5":6,"9":5,"12":1,"19":1,"26":3,"28":2,"29":2}},"SpP32-oVgsE":{"device":{"102":1,"104":2},"os":{"1":1,"4":2}},"Sy_vDZ7kTdA":{"device":{"101":3,"102":1,"103":1,"104":3,"105":1},"os":{"2":3,"4":2,"5":2,"17":1,"28":1}},"TMZRIf5agWM":{"device":{"101":2,"102":1,"104":2},"os":{"2":1,"4":2,"5":1,"9":1}},"TNeD_l-uSXM":{"device":{"104":2},"os":{"5":2}},"TZI4wV5kezI":{"device":{"104":2},"os":{"4":2}},"TnZ5NEzngcs":{"device":{"101":181,"102":28,"103":7,"104":328,"105":21},"os":{"1":3,"2":136,"4":205,"5":156,"9":42,"10":2,"12":8,"17":4,"19":6,"26":1,"27":1,"29":1}},"UF0tXQMP_xw":{"device":{"101":3},"os":{"2":3}},"UKa4Y-eq1hw":{"device":{"101":3,"104":6},"os":{"2":3,"4":2,"5":4}},"UX7ZDsIETg0":{"device":{"104":1},"os":{"5":1}},"Ubo73CUafQ4":{"device":{"101":1,"104":2,"105":1},"os":{"2":1,"4":2,"5":1}},"UfUEBpO2oCw":{"device":{"101":1,"104":3},"os":{"5":3,"30":1}},"Ul-EO4xFtXs":{"device":{"101":20,"103":1,"104":10,"105":3},"os":{"1":1,"2":14,"4":10,"5":3,"9":4,"17":1,"30":1}},"UrgLSEWPteg":{"device":{"101":1},"os":{"2":1}},"V8THWV7wf3c":{"device":{"101":11,"102":2,"103":3,"104":12,"105":11},"os":{"2":11,"4":16,"5":7,"10":2,"17":1,"26":2}},"VhHG2dLDCEc":{"device":{"103":1,"104":1},"os":{"4":1,"17":1}},"VknTKStx1io":{"device":{"101":9,"104":9,"105":3},"os":{"1":1,"2":8,"4":1,"5":11}},"VnAnNOpRDNc":{"device":{"101":18,"102":2,"103":1,"104":12},"os":{"1":2,"2":16,"4":10,"5":2,"10":1,"12":1,"19":1}},"VrslB00QqRM":{"device":{"102":1},"os":{"22":1}},"W_rKM3cjzhg":{"device":{"101":6,"102":1,"104":3},"os":{"2":6,"4":3,"5":1}},"X1mnFMom5ok":{"device":{"101":6,"102":13,"103":3,"104":28,"105":3},"os":{"2":6,"4":16,"5":16,"10":1,"12":4,"17":2,"19":4,"26":3,"29":1}},"XFuEE08kuYU":{"device":{"101":1,"102":1,"104":2},"os":{"2":1,"4":1,"5":1,"26":1}},"XQLgV99UScU":{"device":{"104":2},"os":{"4":1,"5":1}},"XSgRXpf4tMg":{"device":{"101":1},"os":{"2":1}},"XYCsomcgiK8":{"device":{"101":4,"104":1},"os":{"2":4,"5":1}},"XeV_qdcRyYY":{"device":{"101":1,"102":1,"104":1},"os":{"4":1,"19":1,"30":1}},"XzAx_d7EF6s":{"device":{"101":4,"102":1,"104":3,"105":1},"os":{"2":4,"4":1,"5":3,"19":1}},"YDcuYSupxis":{"device":{"101":4,"104":4,"105":1},"os":{"2":4,"4":4,"5":1}},"YFHijQYh5qI":{"device":{"101":16,"104":5},"os":{"2":14,"4":2,"5":3,"9":2}},"YGS9ysr8KTE":{"device":{"101":2},"os":{"2":2}},"YXM1NEYHgbI":{"device":{"104":1},"os":{"5":1}},"YdVJZJtu6TQ":{"device":{"101":9,"104":12},"os":{"2":8,"4":9,"5":3,"9":1}},"Z4OglYP-gPk":{"device":{"101":1,"105":2},"os":{"2":1,"4":2}},"Z75c4VT1hjI":{"device":{"101":2,"102":1,"104":7},"os":{"2":2,"4":2,"5":5,"19":1}},"ZivaBPZE8fA":{"device":{"101":31,"102":8,"103":4,"104":100,"105":10},"os":{"1":2,"2":26,"4":57,"5":54,"9":5,"10":2,"17":2,"19":3,"29":2}},"Zk4W2GnXK1g":{"device":{"101":5,"102":1,"104":7,"105":3},"os":{"2":5,"4":6,"5":4,"19":1}},"ZluTGysYIw8":{"device":{"101":8,"102":1,"104":39,"105":2},"os":{"1":1,"2":8,"4":23,"5":18}},"_-omWaKuN3c":{"device":{"101":1,"104":1},"os":{"2":1,"4":1}},"_MBZMcoz7so":{"device":{"101":1,"103":1,"104":4,"105":1},"os":{"2":1,"4":3,"5":2,"10":1}},"_PS0dSP8FS0":{"device":{"101":2,"104":6},"os":{"2":2,"4":4,"5":2}},"_V82MwbAduc":{"device":{"104":1},"os":{"4":1}},"_dqUwHra3II":{"device":{"101":1,"104":1},"os":{"1":1,"5":1}},"_pOVXwY6HWo":{"device":{"101":2,"103":1},"os":{"9":2,"10":1}},"aA68xBsGr2s":{"device":{"101":4,"102":3,"103":1,"104":3,"105":1},"os":{"2":4,"4":1,"5":3,"10":1,"12":1,"19":1,"26":1}},"aBeT6XLdtUE":{"device":{"100":1,"101":268,"102":139,"103":56,"104":683,"105":92},"os":{"1":23,"2":240,"4":457,"5":346,"9":16,"10":23,"12":17,"17":31,"19":37,"21":1,"26":26,"27":2,"28":4,"29":9,"30":7}},"agiuuiZRe7A":{"device":{"104":1},"os":{"4":1}},"aiZR53aD8ps":{"device":{"101":1,"104":5},"os":{"4":4,"5":1,"9":1}},"azb8V9exqBg":{"device":{"101":1},"os":{"2":1}},"b20qh3rko6o":{"device":{"101":7,"102":1,"104":3},"os":{"1":3,"2":4,"4":2,"5":1,"19":1}},"b6AeB2YFv2I":{"device":{"104":1},"os":{"4":1}},"bBD9xsUbTsI":{"device":{"101":1},"os":{"2":1}},"bME_-Y4GU0s":{"device":{"101":219,"102":47,"103":2,"104":126,"105":18},"os":{"1":11,"2":192,"4":114,"5":40,"9":11,"10":2,"12":6,"19":18,"26":3,"28":1,"29":5,"30":9}},"bQbmiQrneG0":{"device":{"101":2,"102":1,"104":4},"os":{"2":2,"4":4,"26":1}},"bUbBeTZX_8Q":{"device":{"101":5,"103":2,"104":3,"105":1},"os":{"2":2,"4":3,"5":1,"9":3,"17":2}},"bYy94Hnq9d8":{"device":{"101":1},"os":{"2":1}},"bm_ixy5asSU":{"device":{"102":1,"104":1},"os":{"4":1,"5":1}},"bvAm2rFaB0I":{"device":{"104":7},"os":{"4":4,"5":3}},"bvBVwvtTBhM":{"device":{"101":3,"104":1,"105":1},"os":{"2":3,"4":1,"5":1}},"c0QuKjiPezw":{"device":{"101":1,"102":1,"104":4,"105":1},"os":{"1":1,"4":2,"5":3,"19":1}},"c6lhCOdZlv8":{"device":{"101":5,"102":2,"104":8,"105":2},"os":{"2":5,"4":5,"5":5,"12":1,"19":1}},"c8uwuKfuLyw":{"device":{"104":2},"os":{"4":1,"5":1}},"cOWPIOmhogY":{"device":{"101":1,"104":6},"os":{"2":1,"4":3,"5":3}},"cUNBI3jG6Ps":{"device":{"101":5,"104":1,"105":1},"os":{"2":5,"5":2}},"ccctpVrxqzE":{"device":{"101":2,"104":2},"os":{"2":2,"4":1,"5":1}},"ctP_u1QhWck":{"device":{"101":31,"102":25,"103":15,"104":84,"105":4},"os":{"1":6,"2":25,"4":51,"5":40,"9":1,"10":3,"12":1,"17":12,"19":3,"21":1,"26":9,"28":1,"29":3,"30":1,"31":2}},"cw3dB9y2Sas":{"device":{"101":948,"102":106,"103":68,"104":2024,"105":142},"os":{"1":34,"2":816,"4":1254,"5":944,"9":93,"10":38,"12":14,"17":26,"19":26,"21":3,"26":6,"27":4,"28":3,"29":15,"30":11,"31":1}},"d9HWFXbhcNw":{"device":{"101":1,"104":1,"105":1},"os":{"4":2,"9":1}},"dTIww4RF-CE":{"device":{"104":3},"os":{"4":1,"5":2}},"dYpjpKSzspM":{"device":{"104":2},"os":{"4":2}},"d_D8e_Sxsus":{"device":{"101":20,"102":3,"104":12,"105":4},"os":{"1":1,"2":18,"4":11,"5":6,"9":1,"19":2}},"dcPJP4Acq28":{"device":{"101":7,"102":4,"103":7,"104":12},"os":{"1":1,"2":7,"4":9,"5":3,"17":7,"19":1,"26":2}},"dcwLTJwNsXo":{"device":{"101":8,"103":4,"104":39,"105":2},"os":{"2":8,"4":26,"5":15,"10":4}},"dds-2H1RRNA":{"device":{"102":1,"103":1},"os":{"10":1,"19":1}},"deLBqE8iM3w":{"device":{"101":1,"102":1,"104":6},"os":{"2":1,"4":3,"5":4}},"e4XTAeFJc94":{"device":{"101":2,"104":1},"os":{"2":2,"4":1}},"e5h_fG6sYlU":{"device":{"104":1},"os":{"4":1}},"eDPcV_imXWE":{"device":{"101":39,"102":4,"103":7,"104":50,"105":1},"os":{"2":38,"4":22,"5":29,"9":1,"10":6,"12":2,"17":1,"29":2}},"eT18m4COayU":{"device":{"101":79,"102":3,"103":3,"104":39,"105":2},"os":{"1":3,"2":74,"4":32,"5":9,"9":2,"17":3,"19":3}},"eXOb0ZvpdJ8":{"device":{"101":1,"102":1,"103":1,"104":6},"os":{"2":1,"4":4,"5":2,"12":1,"17":1}},"eYt3XZcfxh4":{"device":{"101":4,"104":2},"os":{"2":4,"4":1,"5":1}},"eeBVFrBCmZs":{"device":{"101":71,"102":10,"103":7,"104":37,"105":8},"os":{"1":2,"2":68,"4":41,"5":7,"9":1,"10":3,"12":1,"17":4,"19":2,"26":1,"28":1,"29":2}},"eeNVDg_guuE":{"device":{"101":19,"102":7,"103":1,"104":30,"105":3},"os":{"1":1,"2":18,"4":24,"5":12,"9":1,"10":1,"19":1,"26":2}},"ejMVm8OFhl8":{"device":{"101":47,"102":3,"104":14,"105":1},"os":{"1":4,"2":38,"4":11,"5":4,"9":5,"29":3}},"et9pKdAzRbs":{"device":{"100":1,"101":138,"102":30,"103":8,"104":391,"105":13},"os":{"1":5,"2":120,"4":241,"5":177,"9":15,"10":2,"12":4,"17":6,"19":4,"26":5,"28":2}},"f9VQ8HQ87dg":{"device":{"101":2},"os":{"2":2}},"fE4JvGH7fU0":{"device":{"102":1,"105":1},"os":{"4":1,"19":1}},"fFnQIu3WSpA":{"device":{"101":3,"104":4,"105":1},"os":{"2":3,"4":3,"5":2}},"fKMrdsDWc6w":{"device":{"101":1,"104":12},"os":{"2":1,"4":8,"5":4}},"fOEn_38g1Hw":{"device":{"101":1,"102":1,"104":2},"os":{"4":2,"5":1,"9":1}},"fOV0uB5ln1Y":{"device":{"101":69,"102":4,"103":6,"104":61,"105":4},"os":{"1":1,"2":68,"4":39,"5":27,"10":1,"17":5,"19":2,"30":1}},"fOp1Fd1HB70":{"device":{"101":1},"os":{"2":1}},"ffi99h5QamA":{"device":{"102":2,"103":2,"104":1,"105":1},"os":{"5":2,"10":1,"12":2,"17":1}},"fuaj8_EMOFk":{"device":{"101":207,"102":21,"103":2,"104":84,"105":11},"os":{"1":3,"2":200,"4":59,"5":45,"9":3,"12":1,"17":2,"19":5,"26":1,"29":3,"30":2,"31":1}},"fvEclBQyoec":{"device":{"101":1},"os":{"2":1}},"fz-Tx6SW8pA":{"device":{"101":4,"102":1,"104":3},"os":{"1":1,"2":4,"4":3}},"g8A40NY4acw":{"device":{"101":1,"104":1},"os":{"2":1,"4":1}},"gACL9jyzAcE":{"device":{"101":534,"102":51,"103":10,"104":391,"105":49},"os":{"1":10,"2":517,"4":236,"5":214,"9":10,"10":6,"12":5,"17":2,"19":16,"21":2,"26":9,"27":2,"28":2,"29":3,"31":1}},"gDU5zPB2OF8":{"device":{"101":3,"104":3},"os":{"2":3,"4":1,"5":2}},"gE436H8C3VE":{"device":{"101":16,"102":2,"103":2,"104":8,"105":2},"os":{"1":3,"2":12,"4":7,"5":4,"9":1,"17":2,"26":1}},"gFGNQg0NtiU":{"device":{"101":3,"104":4},"os":{"2":3,"4":2,"5":2}},"gNZ6zFJciI4":{"device":{"101":21,"104":11},"os":{"1":1,"2":20,"4":6,"5":5}},"gRK3o2qCcsI":{"device":{"104":2},"os":{"4":2}},"ghVPea4maME":{"device":{"101":1},"os":{"2":1}},"gyy40GHxznk":{"device":{"101":2,"104":2},"os":{"2":2,"4":2}},"h1hq425flmw":{"device":{"101":1},"os":{"2":1}},"h7cQJ4tRkdE":{"device":{"104":2},"os":{"4":1,"5":1}},"hFGfHGyIlm8":{"device":{"101":6,"104":7,"105":6},"os":{"2":6,"4":10,"5":3}},"hKtccKQuNlc":{"device":{"104":2},"os":{"4":1,"5":1}},"hLKl4XVPXsw":{"device":{"101":2,"104":1},"os":{"2":2,"4":1}},"hMMxP6_YHbk":{"device":{"101":1,"104":7},"os":{"2":1,"4":1,"5":6}},"hZ2bgjMaWuY":{"device":{"100":1,"101":467,"102":154,"103":29,"104":791,"105":143},"os":{"1":25,"2":394,"4":491,"5":480,"9":49,"10":13,"12":31,"13":1,"17":14,"19":35,"21":4,"26":19,"27":2,"28":10,"29":9,"30":4,"31":4}},"he88SjSH0mE":{"device":{"104":6},"os":{"4":3,"5":3}},"hlCFtEFay7M":{"device":{"101":1,"104":3,"105":1},"os":{"5":4,"9":1}},"hqd8v6Aan4s":{"device":{"101":189,"102":50,"103":5,"104":174,"105":20},"os":{"1":13,"2":167,"4":131,"5":72,"9":12,"10":1,"12":3,"17":4,"19":20,"26":8,"28":2,"29":5}},"hrCsbxu8qH4":{"device":{"101":390,"102":56,"103":5,"104":187,"105":23},"os":{"1":9,"2":372,"4":159,"5":69,"9":6,"10":3,"12":4,"17":2,"19":12,"21":1,"26":7,"28":3,"29":10,"30":4}},"i-83UOiiHSI":{"device":{"101":2,"104":1},"os":{"2":2,"4":1}},"i0abkPM85A4":{"device":{"104":1},"os":{"5":1}},"i8v4pw53K-8":{"device":{"101":2},"os":{"2":2}},"iJ9KAW5omXc":{"device":{"101":2,"104":5,"105":2},"os":{"2":2,"4":4,"5":3}},"iLr_YGF8F-o":{"device":{"101":1},"os":{"2":1}},"iQJ26MzP-dU":{"device":{"101":2,"102":1,"104":2,"105":1},"os":{"2":2,"4":2,"5":1,"12":1}},"ilfGbDZCXMA":{"device":{"101":13,"102":2,"104":5},"os":{"1":1,"2":12,"4":5,"5":1,"26":1}},"iqJU0Zh9LXA":{"device":{"104":4,"105":1},"os":{"5":5}},"iuE-vx5Fk6U":{"device":{"101":2},"os":{"2":2}},"iye82MlKoIU":{"device":{"101":25,"102":9,"103":7,"104":56,"105":3},"os":{"1":3,"2":23,"4":37,"5":25,"9":2,"10":2,"12":1,"17":5,"19":1,"26":1}},"izvZFfEet5c":{"device":{"101":6,"102":1,"104":4,"105":1},"os":{"2":6,"4":3,"5":2,"26":1}},"j2rQgFRdhm4":{"device":{"101":4,"102":1,"103":1,"104":6},"os":{"2":4,"4":1,"5":5,"10":1,"29":1}},"j75YqjQiGEw":{"device":{"102":3},"os":{"26":3}},"jPxMIS2idxk":{"device":{"104":1},"os":{"5":1}},"jfUx10AMn0Y":{"device":{"101":56,"102":5,"103":2,"104":46,"105":2},"os":{"1":1,"2":52,"4":39,"5":11,"9":3,"10":1,"17":1,"19":1,"26":1,"29":1}},"jgZTl19hxhM":{"device":{"101":9,"103":1,"104":5},"os":{"2":8,"4":1,"5":4,"9":1,"17":1}},"jiGrj-STkMw":{"device":{"101":6,"102":2,"104":19,"105":3},"os":{"2":6,"4":12,"5":11,"26":1}},"jl3A_UIEnbs":{"device":{"101":25,"102":9,"103":3,"104":14,"105":6},"os":{"2":24,"4":17,"5":7,"10":2,"12":1,"17":1,"26":2,"29":2,"30":1}},"jqIEuFSXbCI":{"device":{"101":3,"104":2},"os":{"4":2,"9":3}},"jy0wF_4imv8":{"device":{"101":1,"104":2,"105":3},"os":{"2":1,"4":5}},"kAqCXPSwWfo":{"device":{"104":1},"os":{"5":1}},"kCo55n0hpiU":{"device":{"101":3,"104":8,"105":1},"os":{"2":3,"4":6,"5":3}},"kKmheCn0bTU":{"device":{"101":1,"102":2,"104":4},"os":{"1":1,"2":1,"4":2,"5":2,"26":1}},"kVsqGo7Sew0":{"device":{"101":6},"os":{"2":6}},"lJSADvshKRQ":{"device":{"101":92,"102":18,"103":6,"104":94,"105":13},"os":{"1":2,"2":78,"4":64,"5":51,"9":12,"10":5,"12":1,"17":1,"19":2,"21":2,"26":1,"28":2,"29":1,"30":1}},"lRSOcTl85SI":{"device":{"101":2,"102":1,"103":1,"104":7},"os":{"2":2,"4":6,"5":2,"17":1}},"lfMrcRb47qw":{"device":{"104":3},"os":{"5":3}},"ly7zKDh35V4":{"device":{"104":1},"os":{"5":1}},"m4HxYnNhTSA":{"device":{"101":1,"104":1},"os":{"5":1,"9":1}},"m8CQBAGYON4":{"device":{"101":4,"104":3},"os":{"2":4,"4":1,"5":2}},"mBtyntp0h-A":{"device":{"101":6,"102":2,"104":2},"os":{"2":6,"4":2,"26":1,"29":1}},"mFAa_tywOww":{"device":{"101":2},"os":{"2":1,"9":1}},"mKm7rBGWO3A":{"device":{"102":1,"103":2,"104":3},"os":{"4":2,"5":1,"10":1,"12":1,"17":1}},"mM9yNwIHTgI":{"device":{"101":10,"104":8},"os":{"1":1,"2":9,"4":7,"5":1}},"mS5tTCA0dB0":{"device":{"104":1},"os":{"4":1}},"maRI2WI9Ptc":{"device":{"101":17,"102":1,"103":1,"104":65,"105":4},"os":{"1":1,"2":12,"4":46,"5":23,"9":4,"17":1,"19":1}},"md1PH6d_Wr0":{"device":{"101":1,"103":1,"104":2},"os":{"2":1,"4":1,"5":1,"17":1}},"mxykcfi8tHk":{"device":{"101":86,"103":4,"104":50,"105":8},"os":{"1":1,"2":83,"4":41,"5":17,"9":2,"17":4}},"mzj9UOT33gE":{"device":{"101":1,"104":8},"os":{"2":1,"4":3,"5":5}},"nHw9fqsVhpk":{"device":{"101":4,"102":1,"103":2,"104":9,"105":2},"os":{"2":4,"4":7,"5":4,"10":2,"19":1}},"nInaxctSw7A":{"device":{"104":2},"os":{"4":2}},"nbE9MsgH1zQ":{"device":{"101":4,"104":1},"os":{"2":4,"5":1}},"nfplGZUSKR4":{"device":{"101":6,"102":5,"103":2,"104":13,"105":1},"os":{"2":6,"4":10,"5":5,"10":2,"26":1,"29":2,"31":1}},"nosJgOtAaGs":{"device":{"101":1},"os":{"2":1}},"oKtLrm0ogG0":{"device":{"101":3,"104":4},"os":{"2":3,"4":1,"5":3}},"oS4ot4lxGkA":{"device":{"101":4,"104":6},"os":{"2":4,"4":4,"5":2}},"ovt9tplYrc0":{"device":{"103":1},"os":{"10":1}},"p2ktK7QefSU":{"device":{"104":1},"os":{"5":1}},"pY0SQsn252Q":{"device":{"101":3,"103":1,"104":8},"os":{"2":3,"4":6,"5":2,"17":1}},"pcl5uVljLak":{"device":{"101":1},"os":{"2":1}},"ph8W9vb04sc":{"device":{"101":11,"102":3,"103":2,"104":12,"105":1},"os":{"1":1,"2":9,"4":6,"5":7,"9":1,"17":2,"19":1,"26":1,"29":1}},"pjNECZsShyw":{"device":{"101":7,"102":1,"104":17},"os":{"2":5,"4":8,"5":9,"9":2,"31":1}},"pv9mmWr0RaU":{"device":{"104":2},"os":{"5":2}},"pxFyOfqcu7M":{"device":{"101":12,"103":3,"104":7},"os":{"1":1,"2":9,"4":2,"5":5,"9":2,"10":2,"17":1}},"pzd7W_Zl_pw":{"device":{"101":90,"102":17,"103":3,"104":58,"105":7},"os":{"1":2,"2":82,"4":53,"5":17,"9":5,"10":3,"12":4,"19":2,"26":1,"28":1,"29":4,"30":1}},"q56usfyjaqk":{"device":{"101":7,"102":1,"103":1,"104":11},"os":{"1":1,"2":4,"4":5,"5":6,"9":1,"17":1,"19":1,"30":1}},"q8bK2JpEZuI":{"device":{"104":1},"os":{"4":1}},"qAEFtjIZTRU":{"device":{"101":22,"104":11},"os":{"2":22,"4":6,"5":5}},"qDd0rxiF6GI":{"device":{"101":115,"102":83,"103":43,"104":169,"105":21},"os":{"1":8,"2":103,"4":121,"5":85,"9":8,"10":19,"12":19,"17":24,"19":16,"26":14,"28":1,"29":10,"30":2,"31":1}},"qKSUtMT6P3s":{"device":{"101":1,"102":1,"103":2},"os":{"2":1,"17":2,"28":1}},"qU8hOWtn_H8":{"device":{"101":2,"102":2,"104":14},"os":{"2":2,"4":6,"5":8,"26":1,"29":1}},"qb76R-s8qj0":{"device":{"101":7,"102":2,"104":2,"105":1},"os":{"2":7,"4":4,"19":1}},"qhcKjsUrrJs":{"device":{"101":4,"102":2,"104":8},"os":{"2":4,"4":8,"19":1,"29":1}},"rfA50754lUk":{"device":{"101":4,"104":4},"os":{"2":4,"4":2,"5":2}},"roJS0yu2OhI":{"device":{"101":24,"103":1,"104":1},"os":{"2":24,"5":1,"10":1}},"ruGFyYyg4dk":{"device":{"101":196,"102":19,"103":3,"104":59,"105":6},"os":{"1":2,"2":192,"4":50,"5":27,"9":2,"10":1,"17":2,"19":3,"26":1,"29":3}},"rzh24aQrMD4":{"device":{"101":44,"102":2,"104":21,"105":2},"os":{"1":3,"2":40,"4":18,"5":5,"9":1,"19":2}},"s6qWEhmG4-4":{"device":{"101":31,"102":5,"103":4,"104":55,"105":10},"os":{"2":26,"4":44,"5":23,"9":5,"10":3,"12":1,"17":1,"19":1,"21":1}},"sCil2OvYJJ0":{"device":{"104":2},"os":{"4":2}},"sJ0dZDYHBuA":{"device":{"102":2,"104":1},"os":{"1":2,"4":1}},"scfiJdkXZsA":{"device":{"101":1,"104":4},"os":{"2":1,"4":4}},"sfXrh2EL-zk":{"device":{"104":2},"os":{"4":2}},"spubr4ivl3s":{"device":{"104":2},"os":{"4":2}},"sxS3it1JTXo":{"device":{"101":1,"104":1},"os":{"2":1,"4":1}},"t-Mp471p2oE":{"device":{"101":2,"102":17,"103":2,"104":19,"105":1},"os":{"1":3,"2":2,"4":12,"5":8,"12":3,"17":2,"19":8,"26":2,"29":1}},"t4ZAt0KmMjQ":{"device":{"101":13,"104":21,"105":1},"os":{"1":1,"2":12,"4":15,"5":7}},"t7C5-A_Rp-s":{"device":{"101":12,"102":1,"103":2,"104":8,"105":4},"os":{"2":12,"4":9,"5":3,"10":1,"12":1,"17":1}},"tA502VldXkw":{"device":{"101":1},"os":{"2":1}},"tOB5pl_CJOI":{"device":{"104":3},"os":{"4":3}},"tXsysReyjkw":{"device":{"101":4,"103":2,"104":3,"105":1},"os":{"2":2,"5":4,"9":2,"17":2}},"tdfe8pM-P1E":{"device":{"101":3,"104":2,"105":1},"os":{"1":1,"2":2,"4":3}},"tirJkYSXZvI":{"device":{"101":10,"104":24},"os":{"2":9,"4":10,"5":14,"9":1}},"tjRdSwIgoWM":{"device":{"101":1,"104":1},"os":{"5":1,"9":1}},"tu1tn2IIGK8":{"device":{"101":1,"103":1,"104":12},"os":{"2":1,"4":8,"5":4,"17":1}},"tzZMmdAu0fM":{"device":{"102":1,"104":1},"os":{"4":1,"12":1}},"tzZPHiV_F8I":{"device":{"101":1,"104":6,"105":1},"os":{"2":1,"4":2,"5":5}},"u7I67LdUZVw":{"device":{"101":7,"104":7},"os":{"2":7,"4":4,"5":3}},"uE4RYCazSsU":{"device":{"104":1},"os":{"4":1}},"uKpMlqA7row":{"device":{"101":17,"102":5,"104":8,"105":1},"os":{"2":16,"4":5,"5":4,"9":1,"12":3,"19":2}},"uLcvlK77WPM":{"device":{"101":98,"104":17,"105":2},"os":{"2":96,"4":12,"5":7,"9":2}},"uYPiiqm_oTU":{"device":{"101":5,"102":1,"104":14},"os":{"1":1,"2":4,"4":8,"5":6,"9":1}},"uZDU-fj7d1o":{"device":{"105":1},"os":{"4":1}},"uZwUrAQmtKo":{"device":{"101":7,"103":2,"104":3,"105":2},"os":{"2":7,"4":3,"5":2,"17":2}},"ux4SvDUqi3w":{"device":{"104":1},"os":{"5":1}},"v36bDCp_a9o":{"device":{"101":1},"os":{"2":1}},"v8XxYlnhfiQ":{"device":{"101":4,"104":4},"os":{"2":4,"4":1,"5":3}},"vOPK8X8bKPU":{"device":{"101":2,"102":1,"104":1},"os":{"2":2,"4":1,"29":1}},"vijhffP1FUY":{"device":{"103":1,"104":1},"os":{"4":1,"10":1}},"vvANTzn-0Nw":{"device":{"101":2,"104":1},"os":{"2":2,"5":1}},"w3CutQDzymI":{"device":{"101":6,"102":1,"104":5,"105":1},"os":{"2":6,"4":5,"5":1,"19":1}},"wHkQIamN-To":{"device":{"102":1,"104":7},"os":{"4":5,"5":3}},"wJSf-j-nIdQ":{"device":{"101":1,"102":2,"104":2,"105":2},"os":{"2":1,"4":3,"5":1,"12":1,"26":1}},"wV2sedXUfKo":{"device":{"104":10},"os":{"4":5,"5":5}},"wb5qzEdLTyU":{"device":{"101":6,"104":11},"os":{"1":1,"2":5,"4":6,"5":5}},"wl3UoSq2C1Y":{"device":{"101":4},"os":{"1":1,"2":3}},"xFR-iPa6-FY":{"device":{"101":1,"105":1},"os":{"2":1,"4":1}},"xKoRmr56LOU":{"device":{"101":3,"104":1},"os":{"2":3,"4":1}},"xKrXUNpDAXI":{"device":{"101":3},"os":{"2":3}},"xKy4e8afJUM":{"device":{"101":9,"102":1,"104":3,"105":1},"os":{"1":1,"2":6,"4":4,"9":2,"26":1}},"xM1u1pUhznI":{"device":{"101":1,"104":2},"os":{"2":1,"4":2}},"xkvlfY-icXM":{"device":{"101":2,"104":2},"os":{"2":2,"5":2}},"xlsRk2WlkI4":{"device":{"101":4,"103":1,"104":9,"105":2},"os":{"2":4,"4":8,"5":3,"10":1}},"ydfF5_M0B4E":{"device":{"101":2},"os":{"2":2}},"z3aFxD7iUSY":{"device":{"100":3,"101":205,"102":56,"103":27,"104":157,"105":30},"os":{"1":17,"2":176,"4":142,"5":50,"9":19,"10":11,"12":8,"17":16,"19":18,"21":3,"26":3,"28":1,"29":9,"30":5}},"z5ujpf1wgGA":{"device":{"101":15,"102":10,"103":4,"104":37,"105":12},"os":{"2":15,"4":35,"5":18,"10":1,"12":1,"17":2,"19":3,"26":1,"27":1,"31":1}},"z7Pm39VM8-0":{"device":{"101":29,"102":9,"103":7,"104":91,"105":7},"os":{"2":26,"4":61,"5":43,"9":3,"10":2,"12":1,"17":5,"19":1,"29":1}},"zI2tl261ap4":{"device":{"101":3,"104":1},"os":{"2":3,"4":1}},"zME3FgQBF_s":{"device":{"101":1,"104":1},"os":{"2":1,"4":1}},"zRUrDjUVc2E":{"device":{"101":31,"102":3,"104":16,"105":3},"os":{"1":2,"2":26,"4":12,"5":7,"9":4,"19":1,"29":1}},"zXNud28NB20":{"device":{"104":1},"os":{"5":1}},"z_jIz8j5_sg":{"device":{"101":8,"102":3,"104":10,"105":2},"os":{"2":8,"4":10,"5":2,"12":1,"19":1,"26":1}},"znlfqiV5tLU":{"device":{"101":2,"104":5},"os":{"2":1,"4":5,"9":1}},"zwu1_ldtVq4":{"device":{"101":1},"os":{"2":1}}}}}